Workbook

Sheet LUS - Pipes
A1: Pipe ID | B1: Installed | C1: Diameter [inch] | D1: Distance until highest point [km] | E1: Longitude [km] | F1: Node connections | G1: Node types | H1: Initial pressure [bar] | I1: Pressure at highest point [bar] | J1: Final pressure [bar] | K1: Lowest pressure [bar] | L1: Initial temperature [°C] | M1: Temperature at critical pressure point [°C] | N1: Final temperature [°C] | O1: Lowest temperature [°C] | P1: Number of boosters | Q1: Booster installation year | R1: Installation Year | S1: Present Value Cost [M€] | T1: Insulated | U1: U-value [W/m^2/K] | V1: Insulation cost [M€] | W1: Booster delta pressure [bar] | X1: Booster delta temperature [°C] | Y1: Flow in 2030 | Z1: Flow in 2035 | AA1: Flow in 2040 | AB1: Flow in 2045 | AC1: Flow in 2050
A2: 25_a | B2: 1 | C2: 38 | D2: 186.05 | E2: 297.08 | F2: (16, 27) | G2: ('E', 'A') | H2: 150 | I2: 87.381501 | J2: 229.19293 | K2: 87.381501 | L2: 45 | M2: 27.095937 | N2: 40.276309 | O2: 27.123708 | P2: 1 | Q2: 2040 | R2: 2040 | S2: 409.55101 | T2: FALSE | U2: 2 | V2: 0 | W2: 50 | X2: 10 | Y2: 0 | Z2: 0 | AA2: 92.246 | AB2: 107.39 | AC2: 110.85
A3: 60_a | B3: 0 | D3: 84.57 | E3: 127.1 | F3: (6, 21) | G3: ('K', 'S') | T3: FALSE
A4: 1_a | B4: 0 | D4: 350.21 | E4: 491.3 | F4: (19, 27) | G4: ('S', 'A') | T4: FALSE
A5: 9_a | B5: 0 | D5: 482.28 | E5: 484.78 | F5: (15, 23) | G5: ('E', 'S') | T5: FALSE
A6: 57_b | B6: 0 | D6: 85.12 | E6: 166.23 | F6: (28, 21) | G6: ('A', 'S') | T6: FALSE
A7: 56_b | B7: 0 | D7: 222.78 | E7: 263.83 | F7: (18, 15) | G7: ('E', 'E') | T7: FALSE
A8: 9_b | B8: 0 | D8: 2.5 | E8: 484.78 | F8: (23, 15) | G8: ('S', 'E') | T8: FALSE
A9: 25_b | B9: 0 | D9: 109.53 | E9: 297.08 | F9: (27, 16) | G9: ('A', 'E') | T9: FALSE
A10: 28_a | B10: 0 | D10: 207.57 | E10: 496.16 | F10: (13, 16) | G10: ('E', 'E') | T10: FALSE
A11: 10_b | B11: 0 | D11: 132.71 | E11: 141.73 | F11: (22, 18) | G11: ('S', 'E') | T11: FALSE
A12: 70_a | B12: 0 | D12: 64.08 | E12: 369.46 | F12: (16, 19) | G12: ('E', 'S') | T12: FALSE
A13: 67_b | B13: 0 | D13: 85.34 | E13: 110.44 | F13: (26, 11) | G13: ('A', 'E') | T13: FALSE
A14: 34_b | B14: 0 | D14: 200.08 | E14: 553.72 | F14: (12, 11) | G14: ('E', 'E') | T14: FALSE
... A37: 41_a | B37: 0 | D37: 0 | E37: 100.6 | F37: (12, 20) | G37: ('E', 'S') | T37: FALSE
A38: 5_a | B38: 1 | C38: 30 | D38: 65.69 | E38: 80.23 | F38: (13, 23) | G38: ('E', 'S') | H38: 150 | I38: 113.38214 | J38: 142.06171 | K38: 113.38214 | L38: 45 | M38: 35.774081 | N38: 37.353685 | O38: 35.145913 | P38: 0 | R38: 2035 | S38: 115.19613 | T38: FALSE | U38: 2 | V38: 0 | Y38: 0 | Z38: 57.46 | AA38: 60.52 | AB38: 63.92 | AC38: 67.67
A39: 7_b | B39: 0 | D39: 167.02 | E39: 518.06 | F39: (17, 6) | G39: ('E', 'K') | T39: FALSE
A40: 14_a | B40: 1 | C40: 26 | D40: 147.03 | E40: 222.05 | F40: (10, 21) | G40: ('E', 'S') | H40: 150 | I40: 78.24019 | J40: 141.68952 | K40: 78.24019 | L40: 45 | M40: 32.339456 | N40: 43.137131 | O40: 31.64011 | P40: 1 | Q40: 2045 | R40: 2045 | S40: 223.74704 | T40: TRUE | U40: 0.43 | V40: 63.927725 | W40: 50 | X40: 10 | Y40: 0 | Z40: 0 | AA40: 0 | AB40: 36.8195 | AC40: 55.110648
A41: 16_a | B41: 0 | D41: 30.51 | E41: 555.74 | F41: (12, 27) | G41: ('E', 'A') | T41: FALSE
A42: 37_b | B42: 0 | D42: 86.53 | E42: 347.61 | F42: (24, 5) | G42: ('S', 'K') | T42: FALSE
A43: 47_a | B43: 0 | D43: 31.51 | E43: 562.63 | F43: (12, 26) | G43: ('E', 'A') | T43: FALSE
A44: 0_b | B44: 0 | D44: 121.13 | E44: 423.46 | F44: (5, 4) | G44: ('K', 'K') | T44: FALSE
A45: 0_a | B45: 0 | D45: 302.33 | E45: 423.46 | F45: (4, 5) | G45: ('K', 'K') | T45: FALSE
A46: 17_a | B46: 0 | D46: 295.43 | E46: 336.49 | F46: (11, 25) | G46: ('E', 'A') | T46: FALSE
A47: 26_a | B47: 0 | D47: 129.2 | E47: 263.91 | F47: (19, 23) | G47: ('S', 'S') | T47: FALSE
A48: 30_a | B48: 0 | D48: 44.01 | E48: 243.08 | F48: (13, 19) | G48: ('E', 'S') | T48: FALSE
A49: 3_b | B49: 1 | C49: 34 | D49: 57.79 | E49: 68.85 | F49: (17, 4) | G49: ('E', 'K') | H49: 150 | I49: 138.18312 | J49: 143.13227 | K49: 138.18312 | L49: 45 | M49: 39.013584 | N49: 38.693962 | O49: 38.535901 | P49: 0 | R49: 2045 | S49: 61.923116 | T49: FALSE | U49: 2 | V49: 0 | Y49: 0 | Z49: 0 | AA49: 0 | AB49: 74.21 | AC49: 75
A50: 32_a | B50: 0 | D50: 303.66 | E50: 345.18 | F50: (5, 21) | G50: ('K', 'S') | T50: FALSE
A51: 49_b | B51: 0 | D51: 48.51 | E51: 302.06 | F51: (25, 17) | G51: ('A', 'E') | T51: FALSE
A52: 47_b | B52: 0 | D52: 530.62 | E52: 562.63 | F52: (26, 12) | G52: ('A', 'E') | T52: FALSE
A53: 31_b | B53: 0 | D53: 142.8 | E53: 228.48 | F53: (22, 15) | G53: ('S', 'E') | T53: FALSE
A54: 2_b | B54: 0 | D54: 328.74 | E54: 448.83 | F54: (11, 4) | G54: ('E', 'K') | T54: FALSE
A55: 4_b | B55: 1 | C55: 30 | D55: 51.62 | E55: 151.35 | F55: (14, 6) | G55: ('E', 'K') | H55: 150 | I55: 105.252 | J55: 195.26472 | K55: 105.252 | L55: 45 | M55: 35.051578 | N55: 34.118409 | O55: 33.907369 | P55: 0 | R55: 2035 | S55: 212.96981 | T55: FALSE | U55: 2 | V55: 0 | Y55: 0 | Z55: 27.132 | AA55: 34.686 | AB55: 0 | AC55: 37.172148
A56: 37_a | B56: 0 | D56: 261.08 | E56: 347.61 | F56: (5, 24) | G56: ('K', 'S') | T56: FALSE
A57: 64_a | B57: 0 | D57: 222.05 | E57: 245.06 | F57: (17, 24) | G57: ('E', 'S') | T57: FALSE
A58: 44_b | B58: 0 | D58: 258.27 | E58: 348.87 | F58: (23, 12) | G58: ('S', 'E') | T58: FALSE
A59: 40_b | B59: 0 | D59: 209.77 | E59: 326.42 | F59: (21, 20) | G59: ('S', 'S') | T59: FALSE
A60: 62_b | B60: 0 | D60: 61.67 | E60: 147.41 | F60: (22, 10) | G60: ('S', 'E') | T60: FALSE
A61: 36_a | B61: 0 | D61: 77.08 | E61: 325.83 | F61: (10, 20) | G61: ('E', 'S') | T61: FALSE
A62: 5_b | B62: 0 | D62: 14.54 | E62: 80.23 | F62: (23, 13) | G62: ('S', 'E') | T62: FALSE
A63: 31_a | B63: 1 | C63: 30 | D63: 85.68 | E63: 228.48 | F63: (15, 22) | G63: ('E', 'S') | H63: 150 | I63: 96.014904 | J63: 157.92772 | K63: 96.014904 | L63: 45 | M63: 36.282553 | N63: 47.696959 | O63: 36.683907 | P63: 1 | Q63: 2050 | R63: 2050 | S63: 201.35992 | T63: TRUE | U63: 0.43 | V63: 57.531404 | W63: 50 | X63: 10 | Y63: 0 | Z63: 0 | AA63: 0 | AB63: 0 | AC63: 73.04
A64: 44_a | B64: 0 | D64: 90.6 | E64: 348.87 | F64: (12, 23) | G64: ('E', 'S') | T64: FALSE
A65: 34_a | B65: 0 | D65: 353.64 | E65: 553.72 | F65: (11, 12) | G65: ('E', 'E') | T65: FALSE
A66: 54_b | B66: 0 | D66: 8.05 | E66: 45.28 | F66: (20, 5) | G66: ('S', 'K') | T66: FALSE
A67: 13_b | B67: 1 | C67: 34 | D67: 183.25 | E67: 343.97 | F67: (22, 20) | G67: ('S', 'S') | H67: 177.42878 | I67: 84.595637 | J67: 192.1278 | K67: 84.595637 | L67: 48.50517 | M67: 25.442423 | N67: 36.785659 | O67: 25.293758 | P67: 1 | Q67: 2050 | R67: 2050 | S67: 244.00848 | T67: FALSE | U67: 2 | V67: 0 | W67: 50 | X67: 10 | Y67: 0 | Z67: 0 | AA67: 0 | AB67: 0 | AC67: 0
A68: 59_b | B68: 0 | D68: 154.52 | E68: 356.04 | F68: (20, 18) | G68: ('S', 'E') | T68: FALSE
A69: 19_b | B69: 0 | D69: 75.61 | E69: 130.7 | F69: (24, 14) | G69: ('S', 'E') | T69: FALSE
A70: 7_a | B70: 0 | D70: 351.04 | E70: 518.06 | F70: (6, 17) | G70: ('K', 'E') | T70: FALSE
A71: 13_a | B71: 0 | D71: 160.72 | E71: 343.97 | F71: (20, 22) | G71: ('S', 'S') | T71: FALSE
A72: 23_a | B72: 1 | C72: 26 | D72: 38.1 | E72: 179.47 | F72: (14, 21) | G72: ('E', 'S') | H72: 150 | I72: 109.76668 | J72: 140.18059 | K72: 109.76668 | L72: 45 | M72: 38.838994 | N72: 41.308749 | O72: 39.444557 | P72: 0 | R72: 2030 | S72: 408.55501 | T72: TRUE | U72: 0.43 | V72: 116.73 | Y72: 49.55 | Z72: 23.598 | AA72: 17.574 | AB72: 54.12 | AC72: 19.147852
A73: 65_a | B73: 0 | D73: 268.79 | E73: 361.88 | F73: (20, 23) | G73: ('S', 'S') | T73: FALSE
A74: 36_b | B74: 0 | D74: 248.75 | E74: 325.83 | F74: (20, 10) | G74: ('S', 'E') | T74: FALSE
A75: 51_b | B75: 0 | D75: 173.15 | E75: 463.4 | F75: (12, 4) | G75: ('E', 'K') | T75: FALSE
A76: 23_b | B76: 0 | D76: 141.37 | E76: 179.47 | F76: (21, 14) | G76: ('S', 'E') | T76: FALSE
A77: 51_a | B77: 0 | D77: 290.25 | E77: 463.4 | F77: (4, 12) | G77: ('K', 'E') | T77: FALSE
A78: 68_b | B78: 0 | D78: 160.66 | E78: 189.69 | F78: (19, 12) | G78: ('S', 'E') | T78: FALSE
A79: 57_a | B79: 0 | D79: 80.11 | E79: 166.23 | F79: (21, 28) | G79: ('S', 'A') | T79: FALSE
A80: 54_a | B80: 0 | D80: 37.23 | E80: 45.28 | F80: (5, 20) | G80: ('K', 'S') | T80: FALSE
A81: 63_b | B81: 0 | D81: 134.62 | E81: 447.89 | F81: (17, 11) | G81: ('E', 'E') | T81: FALSE
A82: 50_b | B82: 0 | D82: 332.5 | E82: 561.51 | F82: (15, 13) | G82: ('E', 'E') | T82: FALSE
A83: 70_b | B83: 0 | D83: 305.38 | E83: 369.46 | F83: (19, 16) | G83: ('S', 'E') | T83: FALSE
A84: 67_a | B84: 1 | C84: 42 | D84: 12.05 | E84: 110.44 | F84: (11, 26) | G84: ('E', 'A') | H84: 150 | I84: 111.45129 | J84: 151.59615 | K84: 111.45129 | L84: 45 | M84: 39.170461 | N84: 38.897364 | O84: 38.937453 | P84: 0 | R84: 2035 | S84: 216.29825 | T84: FALSE | U84: 2 | V84: 0 | Y84: 0 | Z84: 131.504 | AA84: 131.33 | AB84: 128.46 | AC84: 127.07
A85: 60_b | B85: 0 | D85: 42.53 | E85: 127.1 | F85: (21, 6) | G85: ('S', 'K') | T85: FALSE
A86: 61_b | B86: 0 | D86: 4 | E86: 233.52 | F86: (23, 18) | G86: ('S', 'E') | T86: FALSE
A87: 58_b | B87: 0 | D87: 25.02 | E87: 189.66 | F87: (24, 4) | G87: ('S', 'K') | T87: FALSE
A88: 29_b | B88: 1 | C88: 22 | D88: 0 | E88: 78.12 | F88: (12, 5) | G88: ('E', 'K') | H88: 150 | I88: 150 | J88: 177.6889 | K88: 150 | L88: 45 | M88: 45 | N88: 35.154437 | O88: 35.168495 | P88: 0 | R88: 2040 | S88: 70.011105 | T88: FALSE | U88: 2 | V88: 0 | Y88: 0 | Z88: 0 | AA88: 25.8 | AB88: 25.8265 | AC88: 28.2
A89: 4_a | B89: 0 | D89: 99.73 | E89: 151.35 | F89: (6, 14) | G89: ('K', 'E') | T89: FALSE
A90: 17_b | B90: 0 | D90: 40.56 | E90: 336.49 | F90: (25, 11) | G90: ('A', 'E') | T90: FALSE
A91: 63_a | B91: 0 | D91: 313.27 | E91: 447.89 | F91: (11, 17) | G91: ('E', 'E') | T91: FALSE
A92: 1_b | B92: 0 | D92: 140.08 | E92: 491.3 | F92: (27, 19) | G92: ('A', 'S') | T92: FALSE
A93: 43_b | B93: 0 | D93: 221.62 | E93: 370.19 | F93: (17, 14) | G93: ('E', 'E') | T93: FALSE
A94: 59_a | B94: 0 | D94: 201.52 | E94: 356.04 | F94: (18, 20) | G94: ('E', 'S') | T94: FALSE
A95: 10_a | B95: 1 | C95: 22 | D95: 9.01 | E95: 141.73 | F95: (18, 22) | G95: ('E', 'S') | H95: 150 | I95: 127.65952 | J95: 127.42878 | K95: 127.42878 | L95: 45 | M95: 38.548502 | N95: 38.50517 | O95: 38.81206 | P95: 1 | Q95: 2050 | R95: 2030 | S95: 269.33298 | T95: TRUE | U95: 0.43 | V95: 76.952281 | W95: 50 | X95: 10 | Y95: 19.638 | Z95: 0 | AA95: 27.61 | AB95: 28.51 | AC95: 29.59
A96: 14_b | B96: 0 | D96: 75.02 | E96: 222.05 | F96: (21, 10) | G96: ('S', 'E') | T96: FALSE
A97: 58_a | B97: 0 | D97: 164.64 | E97: 189.66 | F97: (4, 24) | G97: ('K', 'S') | T97: FALSE
A98: 11_b | B98: 0 | D98: 0 | E98: 24.61 | F98: (25, 1) | G98: ('A', 'S')
A99: 20_b | B99: 1 | C99: 38 | D99: 0 | E99: 25.42 | F99: (27, 3) | G99: ('A', 'S') | H99: 229.19293 | J99: 226.87293 | K99: 226.87293 | L99: 40.276309 | N99: 32 | P99: 0 | R99: 2040 | S99: 66.686421 | V99: 0 | Y99: 0 | Z99: 0 | AA99: 92.246 | AB99: 107.39 | AC99: 110.85
A100: 52_a | B100: 0 | D100: 0 | E100: 25.73 | F100: (2, 26) | G100: ('S', 'A')
A101: 18_a | B101: 0 | D101: 0 | E101: 135.33 | F101: (9, 28) | G101: ('E', 'A')
A102: 18_b | B102: 0 | D102: 0 | E102: 135.33 | F102: (28, 9) | G102: ('A', 'E')
A103: 52_b | B103: 1 | C103: 42 | D103: 0 | E103: 25.73 | F103: (26, 2) | G103: ('A', 'S') | H103: 151.59615 | J103: 149.50615 | K103: 149.50615 | L103: 38.897364 | N103: 32 | P103: 0 | R103: 2035 | S103: 98.422962 | V103: 0 | Y103: 0 | Z103: 131.504 | AA103: 131.33 | AB103: 128.46 | AC103: 127.07
A104: 46_b | B104: 0 | D104: 0 | E104: 161.79 | F104: (8, 7) | G104: ('E', 'E')
A105: 71_b | B105: 0 | D105: 0 | E105: 192.08 | F105: (9, 8) | G105: ('E', 'E')
A106: 11_a | B106: 0 | D106: 0 | E106: 24.61 | F106: (1, 25) | G106: ('S', 'A')
A107: 20_a | B107: 0 | D107: 0 | E107: 25.42 | F107: (3, 27) | G107: ('S', 'A')
A108: 71_a | B108: 0 | D108: 0 | E108: 192.08 | F108: (8, 9) | G108: ('E', 'E')
A109: 46_a | B109: 0 | D109: 0 | E109: 161.79 | F109: (7, 8) | G109: ('E', 'E')

Sheet LUS - Sinks capacity evolution
A1: Sink node | B1: Initial capacity [Mt] | C1: 2030 capacity [Mt] | D1: 2035 capacity [Mt] | E1: 2040 capacity [Mt] | F1: 2045 capacity [Mt] | G1: 2050 capacity [Mt] | H1: Final capacity [Mt]
A2: 1 | B2: 1250 | C2: 1250 | D2: 1250 | E2: 1250 | F2: 1250 | G2: 1250 | H2: 1250
A3: 2 | B3: 3790 | C3: 3790 | D3: 3790 | E3: 3658.496 | F3: 3527.166 | G3: 3398.706 | H3: 3271.636
A4: 3 | B4: 2100 | C4: 2100 | D4: 2100 | E4: 2100 | F4: 2007.754 | G4: 1900.364 | H4: 1789.514
A5: 19 | B5: 6655.37 | C5: 6655.37 | D5: 6655.37 | E5: 6655.37 | F5: 6655.37 | G5: 6655.37 | H5: 6655.37
A6: 20 | B6: 4571.37 | C6: 4571.37 | D6: 4571.37 | E6: 4571.37 | F6: 4571.37 | G6: 4571.37 | H6: 4571.37
A7: 21 | B7: 1372.72 | C7: 1372.72 | D7: 1323.17 | E7: 1299.572 | F7: 1281.998 | G7: 1191.0585 | H7: 1116.8
A8: 22 | B8: 2171.48 | C8: 2171.48 | D8: 2151.842 | E8: 2151.842 | F8: 2124.232 | G8: 2095.722 | H8: 1993.092
A9: 23 | B9: 4632.05 | C9: 4632.05 | D9: 4632.05 | E9: 4574.59 | F9: 4514.07 | G9: 4450.15 | H9: 4382.48
A10: 24 | B10: 1319.75 | C10: 1319.75 | D10: 1319.75 | E10: 1319.75 | F10: 1319.75 | G10: 1319.75 | H10: 1319.75

Sheet LUS - Utilization evolution
A1: Utilization node | B1: Utilization capacity [Mt] | C1: 2030 utilization [Mt] | D1: 2035 utilization [Mt] | E1: 2040 utilization [Mt] | F1: 2045 utilization [Mt] | G1: 2050 utilization [Mt]
A2: 4 | B2: 75 | C2: 0 | D2: 0 | E2: 0 | F2: 74.21 | G2: 75
A3: 5 | B3: 37.5 | C3: 0 | D3: 0 | E3: 25.8 | F3: 25.8265 | G3: 28.2
A4: 6 | B4: 37.5 | C4: 0 | D4: 27.132 | E4: 34.686 | F4: 0 | G4: 37.172148

Sheet LUS - Cost breakdown
A1: Concept | B1: 2030 | C1: 2035 | D1: 2040 | E1: 2045 | F1: 2050 | G1: Total
A2: Capture cost | B2: 5288.0388 | C2: 13885.473 | D2: 17114.625 | E2: 17286.032 | F2: 15714.522 | G2: 69288.691
A3: Injection cost | B3: 453.1814 | C3: 1054.3075 | D3: 1241.3856 | E3: 1194.7756 | F3: 1042.1536 | G3: 4985.8037
A4: CAPEX onshore pipe | B4: 677.888 | C4: 544.46419 | D4: 479.56211 | E4: 285.67015 | F4: 445.3684 | G4: 2432.9528
A5: CAPEX onshore pipe (insulation only) | B5: 193.68229 | C5: 0 | D5: 0 | E5: 63.927725 | F5: 57.531404 | G5: 315.14141
A6: CAPEX offshore pipe | B6: 0 | C6: 98.422962 | D6: 66.686421 | E6: 0 | F6: 0 | G6: 165.10938
A7: CAPEX initial boosting stations | B7: 4983.8968 | C7: 9224.8657 | D7: 4634.8146 | E7: 3484.4341 | F7: 1398.8621 | G7: 23726.873
A8: CAPEX additional boosting stations | B8: 0 | C8: 0 | D8: 247.333 | E8: 87.736152 | F8: 249.93657 | G8: 585.00573
A9: OPEX onshore pipe | B9: 88.125663 | C9: 137.58001 | D9: 166.6277 | E9: 163.44101 | F9: 181.78759 | G9: 737.56196
A10: OPEX onshore pipe (insulation only) | B10: 25.178761 | C10: 19.085565 | D10: 14.466645 | E10: 19.276042 | F10: 22.090862 | G10: 100.09787
A11: OPEX offshore pipe | B11: 0 | C11: 12.795014 | D11: 18.367903 | E11: 13.9229 | F11: 10.553524 | G11: 55.639341
A12: OPEX initial boosting stations | B12: 134.62097 | C12: 351.27972 | D12: 391.266 | E12: 390.5473 | F12: 333.82173 | G12: 1601.5357
A13: OPEX additional boosting stations | B13: 0 | C13: 0 | D13: 6.3569644 | E13: 7.0861206 | F13: 11.777048 | G13: 25.220133
... A19: TOTAL | B19: 57951.884 | C19: 50625.666 | D19: 36798.115 | E19: 28561.359 | F19: 18187.898 | G19: 192124.92

Sheet EUS - Pipes
A1: Pipe ID | B1: Length [km] | C1: Installed | D1: Diameter [inch] | E1: Distance until highest point [km] | F1: Longitude [km] | G1: Node connections | H1: Node types | I1: Initial pressure [bar] | J1: Pressure at highest point [bar] | K1: Final pressure [bar] | L1: Lowest pressure [bar] | M1: Initial temperature [°C] | N1: Temperature at critical pressure point [°C] | O1: Final temperature [°C] | P1: Lowest temperature [°C] | Q1: Number of boosters | R1: Booster installation year | S1: Installation Year | T1: Present Value Cost [M€] | U1: Insulated | V1: U-value [W/m^2/K] | W1: Insulation cost [M€] | X1: Booster delta pressure [bar] | Y1: Booster delta temperature [°C] | Z1: Flow in 2030 | AA1: Flow in 2035 | AB1: Flow in 2040 | AC1: Flow in 2045 | AD1: Flow in 2050
A2: 25_a | B2: =VLOOKUP(A2,PIPE!A:D,4,0) -> 297.08 | C2: 1 | D2: 38 | E2: 186.05 | F2: 297.08 | G2: (16, 27) | H2: ('E', 'A') | I2: 150 | J2: 87.381501 | K2: 229.19293 | L2: 87.381501 | M2: 45 | N2: 27.095937 | O2: 40.276309 | P2: 27.123708 | Q2: 1 | R2: 2040 | S2: 2040 | T2: 409.55101 | U2: FALSE | V2: 2 | W2: 0 | X2: 50 | Y2: 10 | Z2: 0 | AA2: 0 | AB2: 104.64 | AC2: 107.39 | AD2: 110.85
A3: 60_a | B3: =VLOOKUP(A3,PIPE!A:D,4,0) -> 127.1 | C3: 0 | E3: 84.57 | F3: 127.1 | G3: (6, 21) | H3: ('K', 'S') | U3: FALSE
A4: 1_a | B4: =VLOOKUP(A4,PIPE!A:D,4,0) -> 491.3 | C4: 0 | E4: 350.21 | F4: 491.3 | G4: (19, 27) | H4: ('S', 'A') | U4: FALSE
A5: 9_a | B5: =VLOOKUP(A5,PIPE!A:D,4,0) -> 484.78 | C5: 0 | E5: 482.28 | F5: 484.78 | G5: (15, 23) | H5: ('E', 'S') | U5: FALSE
A6: 57_b | B6: =VLOOKUP(A6,PIPE!A:D,4,0) -> 166.23 | C6: 0 | E6: 85.12 | F6: 166.23 | G6: (28, 21) | H6: ('A', 'S') | U6: FALSE
A7: 56_b | B7: =VLOOKUP(A7,PIPE!A:D,4,0) -> 263.83 | C7: 0 | E7: 222.78 | F7: 263.83 | G7: (18, 15) | H7: ('E', 'E') | U7: FALSE
A8: 9_b | B8: =VLOOKUP(A8,PIPE!A:D,4,0) -> 484.78 | C8: 0 | E8: 2.5 | F8: 484.78 | G8: (23, 15) | H8: ('S', 'E') | U8: FALSE
A9: 25_b | B9: =VLOOKUP(A9,PIPE!A:D,4,0) -> 297.08 | C9: 0 | E9: 109.53 | F9: 297.08 | G9: (27, 16) | H9: ('A', 'E') | U9: FALSE
A10: 28_a | B10: =VLOOKUP(A10,PIPE!A:D,4,0) -> 496.16 | C10: 0 | E10: 207.57 | F10: 496.16 | G10: (13, 16) | H10: ('E', 'E') | U10: FALSE
A11: 10_b | B11: =VLOOKUP(A11,PIPE!A:D,4,0) -> 141.73 | C11: 0 | E11: 132.71 | F11: 141.73 | G11: (22, 18) | H11: ('S', 'E') | U11: FALSE
A12: 70_a | B12: =VLOOKUP(A12,PIPE!A:D,4,0) -> 369.46 | C12: 0 | E12: 64.08 | F12: 369.46 | G12: (16, 19) | H12: ('E', 'S') | U12: FALSE
A13: 67_b | B13: =VLOOKUP(A13,PIPE!A:D,4,0) -> 110.44 | C13: 0 | E13: 85.34 | F13: 110.44 | G13: (26, 11) | H13: ('A', 'E') | U13: FALSE
A14: 34_b | B14: =VLOOKUP(A14,PIPE!A:D,4,0) -> 553.72 | C14: 0 | E14: 200.08 | F14: 553.72 | G14: (12, 11) | H14: ('E', 'E') | U14: FALSE
... A37: 41_a | B37: =VLOOKUP(A37,PIPE!A:D,4,0) -> 100.6 | C37: 0 | E37: 0 | F37: 100.6 | G37: (12, 20) | H37: ('E', 'S') | U37: FALSE
A38: 5_a | B38: =VLOOKUP(A38,PIPE!A:D,4,0) -> 80.23 | C38: 1 | D38: 30 | E38: 65.69 | F38: 80.23 | G38: (13, 23) | H38: ('E', 'S') | I38: 150 | J38: 113.38214 | K38: 142.06171 | L38: 113.38214 | M38: 45 | N38: 35.774081 | O38: 37.353685 | P38: 35.145913 | Q38: 0 | S38: 2035 | T38: 115.19613 | U38: FALSE | V38: 2 | W38: 0 | Z38: 0 | AA38: 0 | AB38: 0 | AC38: 63.92 | AD38: 67.67
A39: 7_b | B39: =VLOOKUP(A39,PIPE!A:D,4,0) -> 518.06 | C39: 0 | E39: 167.02 | F39: 518.06 | G39: (17, 6) | H39: ('E', 'K') | U39: FALSE
A40: 14_a | B40: =VLOOKUP(A40,PIPE!A:D,4,0) -> 222.05 | C40: 1 | D40: 26 | E40: 147.03 | F40: 222.05 | G40: (10, 21) | H40: ('E', 'S') | I40: 150 | J40: 78.24019 | K40: 141.68952 | L40: 78.24019 | M40: 45 | N40: 32.339456 | O40: 43.137131 | P40: 31.64011 | Q40: 1 | R40: 2045 | S40: 2045 | T40: 223.74704 | U40: TRUE | V40: 0.43 | W40: 63.927725 | X40: 50 | Y40: 10 | Z40: 0 | AA40: 0 | AB40: 0 | AC40: 40.155021 | AD40: 55.110648
A41: 16_a | B41: =VLOOKUP(A41,PIPE!A:D,4,0) -> 555.74 | C41: 0 | E41: 30.51 | F41: 555.74 | G41: (12, 27) | H41: ('E', 'A') | U41: FALSE
A42: 37_b | B42: =VLOOKUP(A42,PIPE!A:D,4,0) -> 347.61 | C42: 0 | E42: 86.53 | F42: 347.61 | G42: (24, 5) | H42: ('S', 'K') | U42: FALSE
A43: 47_a | B43: =VLOOKUP(A43,PIPE!A:D,4,0) -> 562.63 | C43: 0 | E43: 31.51 | F43: 562.63 | G43: (12, 26) | H43: ('E', 'A') | U43: FALSE
A44: 0_b | B44: =VLOOKUP(A44,PIPE!A:D,4,0) -> 423.46 | C44: 0 | E44: 121.13 | F44: 423.46 | G44: (5, 4) | H44: ('K', 'K') | U44: FALSE
A45: 0_a | B45: =VLOOKUP(A45,PIPE!A:D,4,0) -> 423.46 | C45: 0 | E45: 302.33 | F45: 423.46 | G45: (4, 5) | H45: ('K', 'K') | U45: FALSE
A46: 17_a | B46: =VLOOKUP(A46,PIPE!A:D,4,0) -> 336.49 | C46: 0 | E46: 295.43 | F46: 336.49 | G46: (11, 25) | H46: ('E', 'A') | U46: FALSE
A47: 26_a | B47: =VLOOKUP(A47,PIPE!A:D,4,0) -> 263.91 | C47: 0 | E47: 129.2 | F47: 263.91 | G47: (19, 23) | H47: ('S', 'S') | U47: FALSE
A48: 30_a | B48: =VLOOKUP(A48,PIPE!A:D,4,0) -> 243.08 | C48: 0 | E48: 44.01 | F48: 243.08 | G48: (13, 19) | H48: ('E', 'S') | U48: FALSE
A49: 3_b | B49: =VLOOKUP(A49,PIPE!A:D,4,0) -> 68.85 | C49: 1 | D49: 34 | E49: 57.79 | F49: 68.85 | G49: (17, 4) | H49: ('E', 'K') | I49: 150 | J49: 138.18312 | K49: 143.13227 | L49: 138.18312 | M49: 45 | N49: 39.013584 | O49: 38.693962 | P49: 38.535901 | Q49: 0 | S49: 2035 | T49: 107.77334 | U49: FALSE | V49: 2 | W49: 0 | Z49: 0 | AA49: 54.264 | AB49: 71.61 | AC49: 74.21 | AD49: 77.28
A50: 32_a | B50: =VLOOKUP(A50,PIPE!A:D,4,0) -> 345.18 | C50: 0 | E50: 303.66 | F50: 345.18 | G50: (5, 21) | H50: ('K', 'S') | U50: FALSE
A51: 49_b | B51: =VLOOKUP(A51,PIPE!A:D,4,0) -> 302.06 | C51: 0 | E51: 48.51 | F51: 302.06 | G51: (25, 17) | H51: ('A', 'E') | U51: FALSE
A52: 47_b | B52: =VLOOKUP(A52,PIPE!A:D,4,0) -> 562.63 | C52: 0 | E52: 530.62 | F52: 562.63 | G52: (26, 12) | H52: ('A', 'E') | U52: FALSE
A53: 31_b | B53: =VLOOKUP(A53,PIPE!A:D,4,0) -> 228.48 | C53: 0 | E53: 142.8 | F53: 228.48 | G53: (22, 15) | H53: ('S', 'E') | U53: FALSE
A54: 2_b | B54: =VLOOKUP(A54,PIPE!A:D,4,0) -> 448.83 | C54: 1 | D54: 26 | E54: 328.74 | F54: 448.83 | G54: (11, 4) | H54: ('E', 'K') | I54: 150 | J54: 76.394582 | K54: 158.73614 | L54: 76.394582 | M54: 45 | N54: 29.55172 | O54: 42.362227 | P54: 28.952224 | Q54: 1 | R54: 2045 | S54: 2045 | T54: 439.43621 | U54: TRUE | V54: 0.43 | W54: 125.5532 | X54: 50 | Y54: 10 | Z54: 0 | AA54: 0 | AB54: 0 | AC54: 45.329021 | AD54: 53.652628
A55: 4_b | B55: =VLOOKUP(A55,PIPE!A:D,4,0) -> 151.35 | C55: 1 | D55: 30 | E55: 51.62 | F55: 151.35 | G55: (14, 6) | H55: ('E', 'K') | I55: 150 | J55: 105.252 | K55: 195.26472 | L55: 105.252 | M55: 45 | N55: 35.051578 | O55: 34.118409 | P55: 33.907369 | Q55: 0 | S55: 2040 | T55: 161.43178 | U55: FALSE | V55: 2 | W55: 0 | Z55: 0 | AA55: 0 | AB55: 44.674 | AC55: 54.12 | AD55: 56.32
A56: 37_a | B56: =VLOOKUP(A56,PIPE!A:D,4,0) -> 347.61 | C56: 0 | E56: 261.08 | F56: 347.61 | G56: (5, 24) | H56: ('K', 'S') | U56: FALSE
A57: 64_a | B57: =VLOOKUP(A57,PIPE!A:D,4,0) -> 245.06 | C57: 0 | E57: 222.05 | F57: 245.06 | G57: (17, 24) | H57: ('E', 'S') | U57: FALSE
A58: 44_b | B58: =VLOOKUP(A58,PIPE!A:D,4,0) -> 348.87 | C58: 0 | E58: 258.27 | F58: 348.87 | G58: (23, 12) | H58: ('S', 'E') | U58: FALSE
A59: 40_b | B59: =VLOOKUP(A59,PIPE!A:D,4,0) -> 326.42 | C59: 0 | E59: 209.77 | F59: 326.42 | G59: (21, 20) | H59: ('S', 'S') | U59: FALSE
A60: 62_b | B60: =VLOOKUP(A60,PIPE!A:D,4,0) -> 147.41 | C60: 0 | E60: 61.67 | F60: 147.41 | G60: (22, 10) | H60: ('S', 'E') | U60: FALSE
A61: 36_a | B61: =VLOOKUP(A61,PIPE!A:D,4,0) -> 325.83 | C61: 0 | E61: 77.08 | F61: 325.83 | G61: (10, 20) | H61: ('E', 'S') | U61: FALSE
A62: 5_b | B62: =VLOOKUP(A62,PIPE!A:D,4,0) -> 80.23 | C62: 0 | E62: 14.54 | F62: 80.23 | G62: (23, 13) | H62: ('S', 'E') | U62: FALSE
A63: 31_a | B63: =VLOOKUP(A63,PIPE!A:D,4,0) -> 228.48 | C63: 1 | D63: 30 | E63: 85.68 | F63: 228.48 | G63: (15, 22) | H63: ('E', 'S') | I63: 150 | J63: 96.014904 | K63: 157.92772 | L63: 96.014904 | M63: 45 | N63: 36.282553 | O63: 47.696959 | P63: 36.683907 | Q63: 1 | R63: 2050 | S63: 2050 | T63: 201.35992 | U63: TRUE | V63: 0.43 | W63: 57.531404 | X63: 50 | Y63: 10 | Z63: 0 | AA63: 0 | AB63: 0 | AC63: 0 | AD63: 73.04
A64: 44_a | B64: =VLOOKUP(A64,PIPE!A:D,4,0) -> 348.87 | C64: 0 | E64: 90.6 | F64: 348.87 | G64: (12, 23) | H64: ('E', 'S') | U64: FALSE
A65: 34_a | B65: =VLOOKUP(A65,PIPE!A:D,4,0) -> 553.72 | C65: 0 | E65: 353.64 | F65: 553.72 | G65: (11, 12) | H65: ('E', 'E') | U65: FALSE
A66: 54_b | B66: =VLOOKUP(A66,PIPE!A:D,4,0) -> 45.28 | C66: 1 | D66: 30 | E66: 8.05 | F66: 45.28 | G66: (20, 5) | H66: ('S', 'K') | I66: 192.1278 | J66: 190.24211 | K66: 197.89641 | L66: 190.24211 | M66: 36.785659 | N66: 35.643533 | O66: 32.497216 | P66: 32.57131 | Q66: 0 | S66: 2050 | T66: 27.884181 | U66: FALSE | V66: 2 | W66: 0 | Z66: 0 | AA66: 0 | AB66: 0 | AC66: 0 | AD66: 48.586021
A67: 13_b | B67: =VLOOKUP(A67,PIPE!A:D,4,0) -> 343.97 | C67: 1 | D67: 34 | E67: 183.25 | F67: 343.97 | G67: (22, 20) | H67: ('S', 'S') | I67: 177.42878 | J67: 84.595637 | K67: 192.1278 | L67: 84.595637 | M67: 48.50517 | N67: 25.442423 | O67: 36.785659 | P67: 25.293758 | Q67: 1 | R67: 2050 | S67: 2050 | T67: 244.00848 | U67: FALSE | V67: 2 | W67: 0 | X67: 50 | Y67: 10 | Z67: 0 | AA67: 0 | AB67: 0 | AC67: 0 | AD67: 48.586021
A68: 59_b | B68: =VLOOKUP(A68,PIPE!A:D,4,0) -> 356.04 | C68: 0 | E68: 154.52 | F68: 356.04 | G68: (20, 18) | H68: ('S', 'E') | U68: FALSE
A69: 19_b | B69: =VLOOKUP(A69,PIPE!A:D,4,0) -> 130.7 | C69: 0 | E69: 75.61 | F69: 130.7 | G69: (24, 14) | H69: ('S', 'E') | U69: FALSE
A70: 7_a | B70: =VLOOKUP(A70,PIPE!A:D,4,0) -> 518.06 | C70: 0 | E70: 351.04 | F70: 518.06 | G70: (6, 17) | H70: ('K', 'E') | U70: FALSE
A71: 13_a | B71: =VLOOKUP(A71,PIPE!A:D,4,0) -> 343.97 | C71: 0 | E71: 160.72 | F71: 343.97 | G71: (20, 22) | H71: ('S', 'S') | U71: FALSE
A72: 23_a | B72: =VLOOKUP(A72,PIPE!A:D,4,0) -> 179.47 | C72: 1 | D72: 26 | E72: 38.1 | F72: 179.47 | G72: (14, 21) | H72: ('E', 'S') | I72: 150 | J72: 109.76668 | K72: 140.18059 | L72: 109.76668 | M72: 45 | N72: 38.838994 | O72: 41.308749 | P72: 39.444557 | Q72: 0 | S72: 2030 | T72: 408.55501 | U72: TRUE | V72: 0.43 | W72: 116.73 | Z72: 49.55 | AA72: 50.73 | AB72: 7.586 | AC72: 0 | AD72: 0
A73: 65_a | B73: =VLOOKUP(A73,PIPE!A:D,4,0) -> 361.88 | C73: 0 | E73: 268.79 | F73: 361.88 | G73: (20, 23) | H73: ('S', 'S') | U73: FALSE
A74: 36_b | B74: =VLOOKUP(A74,PIPE!A:D,4,0) -> 325.83 | C74: 0 | E74: 248.75 | F74: 325.83 | G74: (20, 10) | H74: ('S', 'E') | U74: FALSE
A75: 51_b | B75: =VLOOKUP(A75,PIPE!A:D,4,0) -> 463.4 | C75: 0 | E75: 173.15 | F75: 463.4 | G75: (12, 4) | H75: ('E', 'K') | U75: FALSE
A76: 23_b | B76: =VLOOKUP(A76,PIPE!A:D,4,0) -> 179.47 | C76: 0 | E76: 141.37 | F76: 179.47 | G76: (21, 14) | H76: ('S', 'E') | U76: FALSE
A77: 51_a | B77: =VLOOKUP(A77,PIPE!A:D,4,0) -> 463.4 | C77: 0 | E77: 290.25 | F77: 463.4 | G77: (4, 12) | H77: ('K', 'E') | U77: FALSE
A78: 68_b | B78: =VLOOKUP(A78,PIPE!A:D,4,0) -> 189.69 | C78: 0 | E78: 160.66 | F78: 189.69 | G78: (19, 12) | H78: ('S', 'E') | U78: FALSE
A79: 57_a | B79: =VLOOKUP(A79,PIPE!A:D,4,0) -> 166.23 | C79: 0 | E79: 80.11 | F79: 166.23 | G79: (21, 28) | H79: ('S', 'A') | U79: FALSE
A80: 54_a | B80: =VLOOKUP(A80,PIPE!A:D,4,0) -> 45.28 | C80: 0 | E80: 37.23 | F80: 45.28 | G80: (5, 20) | H80: ('K', 'S') | U80: FALSE
A81: 63_b | B81: =VLOOKUP(A81,PIPE!A:D,4,0) -> 447.89 | C81: 0 | E81: 134.62 | F81: 447.89 | G81: (17, 11) | H81: ('E', 'E') | U81: FALSE
A82: 50_b | B82: =VLOOKUP(A82,PIPE!A:D,4,0) -> 561.51 | C82: 0 | E82: 332.5 | F82: 561.51 | G82: (15, 13) | H82: ('E', 'E') | U82: FALSE
A83: 70_b | B83: =VLOOKUP(A83,PIPE!A:D,4,0) -> 369.46 | C83: 0 | E83: 305.38 | F83: 369.46 | G83: (19, 16) | H83: ('S', 'E') | U83: FALSE
A84: 67_a | B84: =VLOOKUP(A84,PIPE!A:D,4,0) -> 110.44 | C84: 1 | D84: 42 | E84: 12.05 | F84: 110.44 | G84: (11, 26) | H84: ('E', 'A') | I84: 150 | J84: 111.45129 | K84: 151.59615 | L84: 111.45129 | M84: 45 | N84: 39.170461 | O84: 38.897364 | P84: 38.937453 | Q84: 0 | S84: 2035 | T84: 216.29825 | U84: FALSE | V84: 2 | W84: 0 | Z84: 0 | AA84: 135.764 | AB84: 131.33 | AC84: 83.130979 | AD84: 73.417372
A85: 60_b | B85: =VLOOKUP(A85,PIPE!A:D,4,0) -> 127.1 | C85: 1 | D85: 26 | E85: 42.53 | F85: 127.1 | G85: (21, 6) | H85: ('S', 'K') | I85: 141.68952 | J85: 108.61278 | K85: 174.80504 | L85: 108.61278 | M85: 43.137131 | N85: 34.921097 | O85: 32.469952 | P85: 32.442863 | Q85: 0 | S85: 2050 | T85: 72.321194 | U85: FALSE | V85: 2 | W85: 0 | Z85: 0 | AA85: 0 | AB85: 0 | AC85: 0 | AD85: 18.68
A86: 61_b | B86: =VLOOKUP(A86,PIPE!A:D,4,0) -> 233.52 | C86: 0 | E86: 4 | F86: 233.52 | G86: (23, 18) | H86: ('S', 'E') | U86: FALSE
A87: 58_b | B87: =VLOOKUP(A87,PIPE!A:D,4,0) -> 189.66 | C87: 0 | E87: 25.02 | F87: 189.66 | G87: (24, 4) | H87: ('S', 'K') | U87: FALSE
A88: 29_b | B88: =VLOOKUP(A88,PIPE!A:D,4,0) -> 78.12 | C88: 1 | D88: 18 | E88: 0 | F88: 78.12 | G88: (12, 5) | H88: ('E', 'K') | I88: 150 | J88: 150 | K88: 175.60295 | L88: 150 | M88: 45 | N88: 45 | O88: 32.686696 | P88: 32.718705 | Q88: 0 | S88: 2045 | T88: 43.419735 | U88: FALSE | V88: 2 | W88: 0 | Z88: 0 | AA88: 0 | AB88: 0 | AC88: 26.413979 | AD88: 26.413979
A89: 4_a | B89: =VLOOKUP(A89,PIPE!A:D,4,0) -> 151.35 | C89: 0 | E89: 99.73 | F89: 151.35 | G89: (6, 14) | H89: ('K', 'E') | U89: FALSE
A90: 17_b | B90: =VLOOKUP(A90,PIPE!A:D,4,0) -> 336.49 | C90: 0 | E90: 40.56 | F90: 336.49 | G90: (25, 11) | H90: ('A', 'E') | U90: FALSE
A91: 63_a | B91: =VLOOKUP(A91,PIPE!A:D,4,0) -> 447.89 | C91: 0 | E91: 313.27 | F91: 447.89 | G91: (11, 17) | H91: ('E', 'E') | U91: FALSE
A92: 1_b | B92: =VLOOKUP(A92,PIPE!A:D,4,0) -> 491.3 | C92: 0 | E92: 140.08 | F92: 491.3 | G92: (27, 19) | H92: ('A', 'S') | U92: FALSE
A93: 43_b | B93: =VLOOKUP(A93,PIPE!A:D,4,0) -> 370.19 | C93: 0 | E93: 221.62 | F93: 370.19 | G93: (17, 14) | H93: ('E', 'E') | U93: FALSE
A94: 59_a | B94: =VLOOKUP(A94,PIPE!A:D,4,0) -> 356.04 | C94: 0 | E94: 201.52 | F94: 356.04 | G94: (18, 20) | H94: ('E', 'S') | U94: FALSE
A95: 10_a | B95: =VLOOKUP(A95,PIPE!A:D,4,0) -> 141.73 | C95: 1 | D95: 22 | E95: 9.01 | F95: 141.73 | G95: (18, 22) | H95: ('E', 'S') | I95: 150 | J95: 127.65952 | K95: 127.42878 | L95: 127.42878 | M95: 45 | N95: 38.548502 | O95: 38.50517 | P95: 38.81206 | Q95: 1 | R95: 2050 | S95: 2030 | T95: 269.33298 | U95: TRUE | V95: 0.43 | W95: 76.952281 | X95: 50 | Y95: 10 | Z95: 19.638 | AA95: 0 | AB95: 27.61 | AC95: 28.51 | AD95: 29.59
A96: 14_b | B96: =VLOOKUP(A96,PIPE!A:D,4,0) -> 222.05 | C96: 0 | E96: 75.02 | F96: 222.05 | G96: (21, 10) | H96: ('S', 'E') | U96: FALSE
A97: 58_a | B97: =VLOOKUP(A97,PIPE!A:D,4,0) -> 189.66 | C97: 0 | E97: 164.64 | F97: 189.66 | G97: (4, 24) | H97: ('K', 'S') | U97: FALSE
A98: 11_b | B98: =VLOOKUP(A98,PIPE!A:D,4,0) -> 24.61 | C98: 0 | E98: 0 | F98: 24.61 | G98: (25, 1) | H98: ('A', 'S')
A99: 20_b | B99: =VLOOKUP(A99,PIPE!A:D,4,0) -> 25.42 | C99: 1 | D99: 38 | E99: 0 | F99: 25.42 | G99: (27, 3) | H99: ('A', 'S') | I99: 229.19293 | K99: 226.87293 | L99: 226.87293 | M99: 40.276309 | O99: 32 | Q99: 0 | S99: 2040 | T99: 66.686421 | W99: 0 | Z99: 0 | AA99: 0 | AB99: 104.64 | AC99: 107.39 | AD99: 110.85
A100: 52_a | B100: =VLOOKUP(A100,PIPE!A:D,4,0) -> 25.73 | C100: 0 | E100: 0 | F100: 25.73 | G100: (2, 26) | H100: ('S', 'A')
A101: 18_a | B101: =VLOOKUP(A101,PIPE!A:D,4,0) -> 135.33 | C101: 0 | E101: 0 | F101: 135.33 | G101: (9, 28) | H101: ('E', 'A')
A102: 18_b | B102: =VLOOKUP(A102,PIPE!A:D,4,0) -> 135.33 | C102: 0 | E102: 0 | F102: 135.33 | G102: (28, 9) | H102: ('A', 'E')
A103: 52_b | B103: =VLOOKUP(A103,PIPE!A:D,4,0) -> 25.73 | C103: 1 | D103: 42 | E103: 0 | F103: 25.73 | G103: (26, 2) | H103: ('A', 'S') | I103: 151.59615 | K103: 149.50615 | L103: 149.50615 | M103: 38.897364 | O103: 32 | Q103: 0 | S103: 2035 | T103: 98.422962 | W103: 0 | Z103: 0 | AA103: 135.764 | AB103: 131.33 | AC103: 83.130979 | AD103: 73.417372
A104: 46_b | B104: =VLOOKUP(A104,PIPE!A:D,4,0) -> 161.79 | C104: 0 | E104: 0 | F104: 161.79 | G104: (8, 7) | H104: ('E', 'E')
A105: 71_b | B105: =VLOOKUP(A105,PIPE!A:D,4,0) -> 192.08 | C105: 0 | E105: 0 | F105: 192.08 | G105: (9, 8) | H105: ('E', 'E')
A106: 11_a | B106: =VLOOKUP(A106,PIPE!A:D,4,0) -> 24.61 | C106: 0 | E106: 0 | F106: 24.61 | G106: (1, 25) | H106: ('S', 'A')
A107: 20_a | B107: =VLOOKUP(A107,PIPE!A:D,4,0) -> 25.42 | C107: 0 | E107: 0 | F107: 25.42 | G107: (3, 27) | H107: ('S', 'A')
A108: 71_a | B108: =VLOOKUP(A108,PIPE!A:D,4,0) -> 192.08 | C108: 0 | E108: 0 | F108: 192.08 | G108: (8, 9) | H108: ('E', 'E')
A109: 46_a | B109: =VLOOKUP(A109,PIPE!A:D,4,0) -> 161.79 | C109: 0 | E109: 0 | F109: 161.79 | G109: (7, 8) | H109: ('E', 'E')

Sheet PIPE
A1: Pipeline identifier | B1: Node connection | C1: Connection type | D1: Longitude (km)
A2: 0_a | B2: (4, 5) | C2: ('K', 'K') | D2: 423.46
A3: 0_b | B3: (5, 4) | C3: ('K', 'K') | D3: 423.46
A4: 1_a | B4: (19, 27) | C4: ('S', 'A') | D4: 491.3
A5: 1_b | B5: (27, 19) | C5: ('A', 'S') | D5: 491.3
A6: 2_a | B6: (4, 11) | C6: ('K', 'E') | D6: 448.83
A7: 2_b | B7: (11, 4) | C7: ('E', 'K') | D7: 448.83
A8: 3_a | B8: (4, 17) | C8: ('K', 'E') | D8: 68.85
A9: 3_b | B9: (17, 4) | C9: ('E', 'K') | D9: 68.85
A10: 4_a | B10: (6, 14) | C10: ('K', 'E') | D10: 151.35
A11: 4_b | B11: (14, 6) | C11: ('E', 'K') | D11: 151.35
A12: 5_a | B12: (13, 23) | C12: ('E', 'S') | D12: 80.23
A13: 5_b | B13: (23, 13) | C13: ('S', 'E') | D13: 80.23
... A109: 71_b | B109: (9, 8) | C109: ('E', 'E') | D109: 192.08

Sheet EUS - Sinks capacity evolution
A1: Sink node | B1: Initial capacity [Mt] | C1: 2030 capacity [Mt] | D1: 2035 capacity [Mt] | E1: 2040 capacity [Mt] | F1: 2045 capacity [Mt] | G1: 2050 capacity [Mt] | H1: Final capacity [Mt]
A2: 1 | B2: 1250 | C2: 1250 | D2: 1250 | E2: 1250 | F2: 1250 | G2: 1250 | H2: 1250
A3: 2 | B3: 3790 | C3: 3790 | D3: 3790 | E3: 3654.236 | F3: 3522.906 | G3: 3439.775 | H3: 3366.3576
A4: 3 | B4: 2100 | C4: 2100 | D4: 2100 | E4: 2100 | F4: 1995.36 | G4: 1887.97 | H4: 1777.12
A5: 19 | B5: 6655.37 | C5: 6655.37 | D5: 6655.37 | E5: 6655.37 | F5: 6655.37 | G5: 6655.37 | H5: 6655.37
A6: 20 | B6: 4571.37 | C6: 4571.37 | D6: 4571.37 | E6: 4571.37 | F6: 4571.37 | G6: 4571.37 | H6: 4571.37
A7: 21 | B7: 1372.72 | C7: 1372.72 | D7: 1323.17 | E7: 1272.44 | F7: 1264.854 | G7: 1224.699 | H7: 1188.2683
A8: 22 | B8: 2171.48 | C8: 2171.48 | D8: 2151.842 | E8: 2151.842 | F8: 2124.232 | G8: 2095.722 | H8: 2041.678
A9: 23 | B9: 4632.05 | C9: 4632.05 | D9: 4632.05 | E9: 4632.05 | F9: 4632.05 | G9: 4568.13 | H9: 4500.46
A10: 24 | B10: 1319.75 | C10: 1319.75 | D10: 1319.75 | E10: 1319.75 | F10: 1319.75 | G10: 1319.75 | H10: 1319.75

Sheet EUS - Utilization evolution
A1: Utilization node | B1: Utilization capacity [Mt] | C1: 2030 utilization [Mt] | D1: 2035 utilization [Mt] | E1: 2040 utilization [Mt] | F1: 2045 utilization [Mt] | G1: 2050 utilization [Mt]
A2: 4 | B2: 150 | C2: 0 | D2: 54.264 | E2: 71.61 | F2: 119.53902 | G2: 130.93263
A3: 5 | B3: 75 | C3: 0 | D3: 0 | E3: 0 | F3: 26.413979 | G3: 75
A4: 6 | B4: 75 | C4: 0 | D4: 0 | E4: 44.674 | F4: 54.12 | G4: 75

Sheet EUS - Cost breakdown
A1: Concept | B1: 2030 | C1: 2035 | D1: 2040 | E1: 2045 | F1: 2050 | G1: Total
A2: Capture cost | B2: 5288.0388 | C2: 13947.111 | D2: 17012.929 | E2: 17416.629 | F2: 15726.985 | G2: 69391.693
A3: Injection cost | B3: 453.1814 | C3: 925.01024 | D3: 1022.2958 | E3: 920.8521 | F3: 739.60992 | G3: 4060.9495
A4: CAPEX onshore pipe | B4: 677.888 | C4: 439.26772 | D4: 570.98279 | E4: 706.60298 | F4: 545.57377 | G4: 2940.3153
A5: CAPEX onshore pipe (insulation only) | B5: 193.68229 | C5: 0 | D5: 0 | E5: 189.48093 | F5: 57.531404 | G5: 440.69462
A6: CAPEX offshore pipe | B6: 0 | C6: 98.422962 | D6: 66.686421 | E6: 0 | F6: 0 | G6: 165.10938
A7: CAPEX initial boosting stations | B7: 4983.8968 | C7: 9647.4559 | D7: 3694.8522 | E7: 3954.129 | F7: 1398.8621 | G7: 23679.196
A8: CAPEX additional boosting stations | B8: 0 | C8: 0 | D8: 247.333 | E8: 175.4723 | F8: 249.93657 | G8: 672.74188
A9: OPEX onshore pipe | B9: 88.125663 | C9: 123.90442 | D9: 168.14644 | E9: 219.31186 | F9: 237.16492 | G9: 836.65331
A10: OPEX onshore pipe (insulation only) | B10: 25.178761 | C10: 19.085565 | D10: 14.466645 | E10: 35.597508 | F10: 34.462767 | G10: 128.79125
A11: OPEX offshore pipe | B11: 0 | C11: 12.795014 | D11: 18.367903 | E11: 13.9229 | F11: 10.553524 | G11: 55.639341
A12: OPEX initial boosting stations | B12: 134.62097 | C12: 362.6964 | D12: 374.535 | E12: 390.5473 | F12: 333.82173 | G12: 1596.2214
A13: OPEX additional boosting stations | B13: 0 | C13: 0 | D13: 6.3569644 | E13: 9.3456572 | F13: 13.485478 | G13: 29.188099
... A19: TOTAL | B19: 57951.884 | C19: 48657.246 | D19: 32404.287 | E19: 24635.168 | F19: 13192.677 | G19: 176841.26

Sheet HUS - Pipes
A1: Pipe ID | B1: Installed | C1: Diameter [inch] | D1: Distance until highest point [km] | E1: Longitude [km] | F1: Node connections | G1: Node types | H1: Initial pressure [bar] | I1: Pressure at highest point [bar] | J1: Final pressure [bar] | K1: Lowest pressure [bar] | L1: Initial temperature [°C] | M1: Temperature at critical pressure point [°C] | N1: Final temperature [°C] | O1: Lowest temperature [°C] | P1: Number of boosters | Q1: Booster installation year | R1: Installation Year | S1: Present Value Cost [M€] | T1: Insulated | U1: U-value [W/m^2/K] | V1: Insulation cost [M€] | W1: Booster delta pressure [bar] | X1: Booster delta temperature [°C] | Y1: Flow in 2030 | Z1: Flow in 2035 | AA1: Flow in 2040 | AB1: Flow in 2045 | AC1: Flow in 2050
A2: 25_a | B2: 1 | C2: 38 | D2: 186.05 | E2: 297.08 | F2: (16, 27) | G2: ('E', 'A') | H2: 150 | I2: 87.381501 | J2: 229.19293 | K2: 87.381501 | L2: 45 | M2: 27.095937 | N2: 40.276309 | O2: 27.123708 | P2: 1 | Q2: 2040 | R2: 2040 | S2: 409.55101 | T2: FALSE | U2: 2 | V2: 0 | W2: 50 | X2: 10 | Y2: 0 | Z2: 0 | AA2: 104.64 | AB2: 96.357372 | AC2: 110.85
A3: 60_a | B3: 0 | D3: 84.57 | E3: 127.1 | F3: (6, 21) | G3: ('K', 'S') | T3: FALSE
A4: 1_a | B4: 0 | D4: 350.21 | E4: 491.3 | F4: (19, 27) | G4: ('S', 'A') | T4: FALSE
A5: 9_a | B5: 0 | D5: 482.28 | E5: 484.78 | F5: (15, 23) | G5: ('E', 'S') | T5: FALSE
A6: 57_b | B6: 0 | D6: 85.12 | E6: 166.23 | F6: (28, 21) | G6: ('A', 'S') | T6: FALSE
A7: 56_b | B7: 0 | D7: 222.78 | E7: 263.83 | F7: (18, 15) | G7: ('E', 'E') | T7: FALSE
A8: 9_b | B8: 0 | D8: 2.5 | E8: 484.78 | F8: (23, 15) | G8: ('S', 'E') | T8: FALSE
A9: 25_b | B9: 0 | D9: 109.53 | E9: 297.08 | F9: (27, 16) | G9: ('A', 'E') | T9: FALSE
A10: 28_a | B10: 0 | D10: 207.57 | E10: 496.16 | F10: (13, 16) | G10: ('E', 'E') | T10: FALSE
A11: 10_b | B11: 0 | D11: 132.71 | E11: 141.73 | F11: (22, 18) | G11: ('S', 'E') | T11: FALSE
A12: 70_a | B12: 0 | D12: 64.08 | E12: 369.46 | F12: (16, 19) | G12: ('E', 'S') | T12: FALSE
A13: 67_b | B13: 0 | D13: 85.34 | E13: 110.44 | F13: (26, 11) | G13: ('A', 'E') | T13: FALSE
A14: 34_b | B14: 0 | D14: 200.08 | E14: 553.72 | F14: (12, 11) | G14: ('E', 'E') | T14: FALSE
... A37: 41_a | B37: 0 | D37: 0 | E37: 100.6 | F37: (12, 20) | G37: ('E', 'S') | T37: FALSE
A38: 5_a | B38: 1 | C38: 30 | D38: 65.69 | E38: 80.23 | F38: (13, 23) | G38: ('E', 'S') | H38: 150 | I38: 113.38214 | J38: 142.06171 | K38: 113.38214 | L38: 45 | M38: 35.774081 | N38: 37.353685 | O38: 35.145913 | P38: 0 | R38: 2035 | S38: 115.19613 | T38: FALSE | U38: 2 | V38: 0 | Y38: 0 | Z38: 0 | AA38: 0 | AB38: 63.92 | AC38: 67.67
A39: 7_b | B39: 0 | D39: 167.02 | E39: 518.06 | F39: (17, 6) | G39: ('E', 'K') | T39: FALSE
A40: 14_a | B40: 1 | C40: 26 | D40: 147.03 | E40: 222.05 | F40: (10, 21) | G40: ('E', 'S') | H40: 150 | I40: 78.24019 | J40: 141.68952 | K40: 78.24019 | L40: 45 | M40: 32.339456 | N40: 43.137131 | O40: 31.64011 | P40: 1 | Q40: 2045 | R40: 2045 | S40: 223.74704 | T40: TRUE | U40: 0.43 | V40: 63.927725 | W40: 50 | X40: 10 | Y40: 0 | Z40: 0 | AA40: 0 | AB40: 55.110648 | AC40: 55.110648
A41: 16_a | B41: 0 | D41: 30.51 | E41: 555.74 | F41: (12, 27) | G41: ('E', 'A') | T41: FALSE
A42: 37_b | B42: 0 | D42: 86.53 | E42: 347.61 | F42: (24, 5) | G42: ('S', 'K') | T42: FALSE
A43: 47_a | B43: 0 | D43: 31.51 | E43: 562.63 | F43: (12, 26) | G43: ('E', 'A') | T43: FALSE
A44: 0_b | B44: 0 | D44: 121.13 | E44: 423.46 | F44: (5, 4) | G44: ('K', 'K') | T44: FALSE
A45: 0_a | B45: 0 | D45: 302.33 | E45: 423.46 | F45: (4, 5) | G45: ('K', 'K') | T45: FALSE
A46: 17_a | B46: 0 | D46: 295.43 | E46: 336.49 | F46: (11, 25) | G46: ('E', 'A') | T46: FALSE
A47: 26_a | B47: 0 | D47: 129.2 | E47: 263.91 | F47: (19, 23) | G47: ('S', 'S') | T47: FALSE
A48: 30_a | B48: 0 | D48: 44.01 | E48: 243.08 | F48: (13, 19) | G48: ('E', 'S') | T48: FALSE
A49: 3_b | B49: 1 | C49: 34 | D49: 57.79 | E49: 68.85 | F49: (17, 4) | G49: ('E', 'K') | H49: 150 | I49: 138.18312 | J49: 143.13227 | K49: 138.18312 | L49: 45 | M49: 39.013584 | N49: 38.693962 | O49: 38.535901 | P49: 0 | R49: 2035 | S49: 107.77334 | T49: FALSE | U49: 2 | V49: 0 | Y49: 0 | Z49: 65.417173 | AA49: 71.61 | AB49: 74.21 | AC49: 77.28
A50: 32_a | B50: 0 | D50: 303.66 | E50: 345.18 | F50: (5, 21) | G50: ('K', 'S') | T50: FALSE
A51: 49_b | B51: 0 | D51: 48.51 | E51: 302.06 | F51: (25, 17) | G51: ('A', 'E') | T51: FALSE
A52: 47_b | B52: 0 | D52: 530.62 | E52: 562.63 | F52: (26, 12) | G52: ('A', 'E') | T52: FALSE
A53: 31_b | B53: 0 | D53: 142.8 | E53: 228.48 | F53: (22, 15) | G53: ('S', 'E') | T53: FALSE
A54: 2_b | B54: 1 | C54: 42 | D54: 328.74 | E54: 448.83 | F54: (11, 4) | G54: ('E', 'K') | H54: 150 | I54: 89.87825 | J54: 175.79455 | K54: 89.87825 | L54: 45 | M54: 33.375196 | N54: 47.794334 | O54: 33.373565 | P54: 1 | Q54: 2040 | R54: 2040 | S54: 936.4846 | T54: TRUE | U54: 0.43 | V54: 267.56703 | W54: 50 | X54: 10 | Y54: 0 | Z54: 0 | AA54: 86.809173 | AB54: 90.254872 | AC54: 119.78848
A55: 4_b | B55: 1 | C55: 14 | D55: 51.62 | E55: 151.35 | F55: (14, 6) | G55: ('E', 'K') | H55: 150 | I55: 100.15985 | J55: 173.93481 | K55: 100.15985 | L55: 45 | M55: 36.155662 | N55: 40.953324 | O55: 36.810053 | P55: 0 | R55: 2035 | S55: 139.14035 | T55: TRUE | U55: 0.43 | V55: 39.754385 | Y55: 0 | Z55: 15.978827 | AA55: 15.978827 | AB55: 15.978827 | AC55: 1.2093518
A56: 37_a | B56: 0 | D56: 261.08 | E56: 347.61 | F56: (5, 24) | G56: ('K', 'S') | T56: FALSE
A57: 64_a | B57: 0 | D57: 222.05 | E57: 245.06 | F57: (17, 24) | G57: ('E', 'S') | T57: FALSE
A58: 44_b | B58: 0 | D58: 258.27 | E58: 348.87 | F58: (23, 12) | G58: ('S', 'E') | T58: FALSE
A59: 40_b | B59: 0 | D59: 209.77 | E59: 326.42 | F59: (21, 20) | G59: ('S', 'S') | T59: FALSE
A60: 62_b | B60: 0 | D60: 61.67 | E60: 147.41 | F60: (22, 10) | G60: ('S', 'E') | T60: FALSE
A61: 36_a | B61: 0 | D61: 77.08 | E61: 325.83 | F61: (10, 20) | G61: ('E', 'S') | T61: FALSE
A62: 5_b | B62: 0 | D62: 14.54 | E62: 80.23 | F62: (23, 13) | G62: ('S', 'E') | T62: FALSE
A63: 31_a | B63: 1 | C63: 30 | D63: 85.68 | E63: 228.48 | F63: (15, 22) | G63: ('E', 'S') | H63: 150 | I63: 96.014904 | J63: 157.92772 | K63: 96.014904 | L63: 45 | M63: 36.282553 | N63: 47.696959 | O63: 36.683907 | P63: 1 | Q63: 2050 | R63: 2050 | S63: 201.35992 | T63: TRUE | U63: 0.43 | V63: 57.531404 | W63: 50 | X63: 10 | Y63: 0 | Z63: 0 | AA63: 0 | AB63: 0 | AC63: 73.04
A64: 44_a | B64: 0 | D64: 90.6 | E64: 348.87 | F64: (12, 23) | G64: ('E', 'S') | T64: FALSE
A65: 34_a | B65: 0 | D65: 353.64 | E65: 553.72 | F65: (11, 12) | G65: ('E', 'E') | T65: FALSE
A66: 54_b | B66: 1 | C66: 34 | D66: 8.05 | E66: 45.28 | F66: (20, 5) | G66: ('S', 'K') | H66: 192.1278 | I66: 190.33491 | J66: 198.3568 | K66: 190.33491 | L66: 36.785659 | M66: 35.762833 | N66: 33.116321 | O66: 33.182506 | P66: 0 | R66: 2050 | S66: 31.602059 | T66: FALSE | U66: 2 | V66: 0 | Y66: 0 | Z66: 0 | AA66: 0 | AB66: 0 | AC66: 86.086021
A67: 13_b | B67: 1 | C67: 34 | D67: 183.25 | E67: 343.97 | F67: (22, 20) | G67: ('S', 'S') | H67: 177.42878 | I67: 84.595637 | J67: 192.1278 | K67: 84.595637 | L67: 48.50517 | M67: 25.442423 | N67: 36.785659 | O67: 25.293758 | P67: 1 | Q67: 2050 | R67: 2050 | S67: 244.00848 | T67: FALSE | U67: 2 | V67: 0 | W67: 50 | X67: 10 | Y67: 0 | Z67: 0 | AA67: 0 | AB67: 0 | AC67: 86.086021
A68: 59_b | B68: 0 | D68: 154.52 | E68: 356.04 | F68: (20, 18) | G68: ('S', 'E') | T68: FALSE
A69: 19_b | B69: 0 | D69: 75.61 | E69: 130.7 | F69: (24, 14) | G69: ('S', 'E') | T69: FALSE
A70: 7_a | B70: 0 | D70: 351.04 | E70: 518.06 | F70: (6, 17) | G70: ('K', 'E') | T70: FALSE
A71: 13_a | B71: 0 | D71: 160.72 | E71: 343.97 | F71: (20, 22) | G71: ('S', 'S') | T71: FALSE
A72: 23_a | B72: 1 | C72: 26 | D72: 38.1 | E72: 179.47 | F72: (14, 21) | G72: ('E', 'S') | H72: 150 | I72: 109.76668 | J72: 140.18059 | K72: 109.76668 | L72: 45 | M72: 38.838994 | N72: 41.308749 | O72: 39.444557 | P72: 0 | R72: 2030 | S72: 408.55501 | T72: TRUE | U72: 0.43 | V72: 116.73 | Y72: 49.55 | Z72: 24.606 | AA72: 36.281173 | AB72: 38.141173 | AC72: 55.110648
A73: 65_a | B73: 0 | D73: 268.79 | E73: 361.88 | F73: (20, 23) | G73: ('S', 'S') | T73: FALSE
A74: 36_b | B74: 0 | D74: 248.75 | E74: 325.83 | F74: (20, 10) | G74: ('S', 'E') | T74: FALSE
A75: 51_b | B75: 0 | D75: 173.15 | E75: 463.4 | F75: (12, 4) | G75: ('E', 'K') | T75: FALSE
A76: 23_b | B76: 0 | D76: 141.37 | E76: 179.47 | F76: (21, 14) | G76: ('S', 'E') | T76: FALSE
A77: 51_a | B77: 0 | D77: 290.25 | E77: 463.4 | F77: (4, 12) | G77: ('K', 'E') | T77: FALSE
A78: 68_b | B78: 0 | D78: 160.66 | E78: 189.69 | F78: (19, 12) | G78: ('S', 'E') | T78: FALSE
A79: 57_a | B79: 0 | D79: 80.11 | E79: 166.23 | F79: (21, 28) | G79: ('S', 'A') | T79: FALSE
A80: 54_a | B80: 0 | D80: 37.23 | E80: 45.28 | F80: (5, 20) | G80: ('K', 'S') | T80: FALSE
A81: 63_b | B81: 0 | D81: 134.62 | E81: 447.89 | F81: (17, 11) | G81: ('E', 'E') | T81: FALSE
A82: 50_b | B82: 0 | D82: 332.5 | E82: 561.51 | F82: (15, 13) | G82: ('E', 'E') | T82: FALSE
A83: 70_b | B83: 0 | D83: 305.38 | E83: 369.46 | F83: (19, 16) | G83: ('S', 'E') | T83: FALSE
A84: 67_a | B84: 1 | C84: 42 | D84: 12.05 | E84: 110.44 | F84: (11, 26) | G84: ('E', 'A') | H84: 150 | I84: 111.45129 | J84: 151.59615 | K84: 111.45129 | L84: 45 | M84: 39.170461 | N84: 38.897364 | O84: 38.937453 | P84: 0 | R84: 2035 | S84: 216.29825 | T84: FALSE | U84: 2 | V84: 0 | Y84: 0 | Z84: 135.82 | AA84: 44.520827 | AB84: 38.205128 | AC84: 7.2815207
A85: 60_b | B85: 1 | C85: 38 | D85: 42.53 | E85: 127.1 | F85: (21, 6) | G85: ('S', 'K') | H85: 141.68952 | I85: 110.53198 | J85: 178.23198 | K85: 110.53198 | L85: 43.137131 | M85: 36.431137 | N85: 36.75545 | O85: 36.692335 | P85: 0 | R85: 2045 | S85: 139.44557 | T85: FALSE | U85: 2 | V85: 0 | Y85: 0 | Z85: 0 | AA85: 0 | AB85: 93.251821 | AC85: 110.2213
A86: 61_b | B86: 0 | D86: 4 | E86: 233.52 | F86: (23, 18) | G86: ('S', 'E') | T86: FALSE
A87: 58_b | B87: 1 | C87: 6 | D87: 25.02 | E87: 189.66 | F87: (24, 4) | G87: ('S', 'K') | H87: 229.91923 | I87: 172.20197 | J87: 173.13227 | K87: 172.20197 | L87: 79.084695 | M87: 42.643641 | N87: 42.794334 | O87: 42.656283 | P87: 0 | R87: 2040 | S87: 41.632004 | T87: FALSE | U87: 2 | V87: 0 | Y87: 0 | Z87: 0 | AA87: 0 | AB87: 0 | AC87: 0
A88: 29_b | B88: 1 | C88: 18 | D88: 0 | E88: 78.12 | F88: (12, 5) | G88: ('E', 'K') | H88: 150 | I88: 150 | J88: 175.60295 | K88: 150 | L88: 45 | M88: 45 | N88: 32.686696 | O88: 32.718705 | P88: 0 | R88: 2045 | S88: 43.419735 | T88: FALSE | U88: 2 | V88: 0 | Y88: 0 | Z88: 0 | AA88: 0 | AB88: 26.413979 | AC88: 26.413979
A89: 4_a | B89: 0 | D89: 99.73 | E89: 151.35 | F89: (6, 14) | G89: ('K', 'E') | T89: FALSE
A90: 17_b | B90: 0 | D90: 40.56 | E90: 336.49 | F90: (25, 11) | G90: ('A', 'E') | T90: FALSE
A91: 63_a | B91: 0 | D91: 313.27 | E91: 447.89 | F91: (11, 17) | G91: ('E', 'E') | T91: FALSE
A92: 1_b | B92: 0 | D92: 140.08 | E92: 491.3 | F92: (27, 19) | G92: ('A', 'S') | T92: FALSE
A93: 43_b | B93: 0 | D93: 221.62 | E93: 370.19 | F93: (17, 14) | G93: ('E', 'E') | T93: FALSE
A94: 59_a | B94: 0 | D94: 201.52 | E94: 356.04 | F94: (18, 20) | G94: ('E', 'S') | T94: FALSE
A95: 10_a | B95: 1 | C95: 22 | D95: 9.01 | E95: 141.73 | F95: (18, 22) | G95: ('E', 'S') | H95: 150 | I95: 127.65952 | J95: 127.42878 | K95: 127.42878 | L95: 45 | M95: 38.548502 | N95: 38.50517 | O95: 38.81206 | P95: 1 | Q95: 2050 | R95: 2030 | S95: 269.33298 | T95: TRUE | U95: 0.43 | V95: 76.952281 | W95: 50 | X95: 10 | Y95: 19.638 | Z95: 0 | AA95: 27.61 | AB95: 28.51 | AC95: 29.59
A96: 14_b | B96: 0 | D96: 75.02 | E96: 222.05 | F96: (21, 10) | G96: ('S', 'E') | T96: FALSE
A97: 58_a | B97: 0 | D97: 164.64 | E97: 189.66 | F97: (4, 24) | G97: ('K', 'S') | T97: FALSE
A98: 11_b | B98: 0 | D98: 0 | E98: 24.61 | F98: (25, 1) | G98: ('A', 'S')
A99: 20_b | B99: 1 | C99: 38 | D99: 0 | E99: 25.42 | F99: (27, 3) | G99: ('A', 'S') | H99: 229.19293 | J99: 226.87293 | K99: 226.87293 | L99: 40.276309 | N99: 32 | P99: 0 | R99: 2040 | S99: 66.686421 | V99: 0 | Y99: 0 | Z99: 0 | AA99: 104.64 | AB99: 96.357372 | AC99: 110.85
A100: 52_a | B100: 0 | D100: 0 | E100: 25.73 | F100: (2, 26) | G100: ('S', 'A')
A101: 18_a | B101: 0 | D101: 0 | E101: 135.33 | F101: (9, 28) | G101: ('E', 'A')
A102: 18_b | B102: 0 | D102: 0 | E102: 135.33 | F102: (28, 9) | G102: ('A', 'E')
A103: 52_b | B103: 1 | C103: 42 | D103: 0 | E103: 25.73 | F103: (26, 2) | G103: ('A', 'S') | H103: 151.59615 | J103: 149.50615 | K103: 149.50615 | L103: 38.897364 | N103: 32 | P103: 0 | R103: 2035 | S103: 98.422962 | V103: 0 | Y103: 0 | Z103: 135.82 | AA103: 44.520827 | AB103: 38.205128 | AC103: 7.2815207
A104: 46_b | B104: 0 | D104: 0 | E104: 161.79 | F104: (8, 7) | G104: ('E', 'E')
A105: 71_b | B105: 0 | D105: 0 | E105: 192.08 | F105: (9, 8) | G105: ('E', 'E')
A106: 11_a | B106: 0 | D106: 0 | E106: 24.61 | F106: (1, 25) | G106: ('S', 'A')
A107: 20_a | B107: 0 | D107: 0 | E107: 25.42 | F107: (3, 27) | G107: ('S', 'A')
A108: 71_a | B108: 0 | D108: 0 | E108: 192.08 | F108: (8, 9) | G108: ('E', 'E')
A109: 46_a | B109: 0 | D109: 0 | E109: 161.79 | F109: (7, 8) | G109: ('E', 'E')

Sheet HUS - Sinks capacity evolution
A1: Sink node | B1: Initial capacity [Mt] | C1: 2030 capacity [Mt] | D1: 2035 capacity [Mt] | E1: 2040 capacity [Mt] | F1: 2045 capacity [Mt] | G1: 2050 capacity [Mt] | H1: Final capacity [Mt]
A2: 1 | B2: 1250 | C2: 1250 | D2: 1250 | E2: 1250 | F2: 1250 | G2: 1250 | H2: 1250
A3: 2 | B3: 3790 | C3: 3790 | D3: 3790 | E3: 3654.18 | F3: 3609.6592 | G3: 3571.454 | H3: 3564.1725
A4: 3 | B4: 2100 | C4: 2100 | D4: 2100 | E4: 2100 | F4: 1995.36 | G4: 1899.0026 | H4: 1788.1526
A5: 19 | B5: 6655.37 | C5: 6655.37 | D5: 6655.37 | E5: 6655.37 | F5: 6655.37 | G5: 6655.37 | H5: 6655.37
A6: 20 | B6: 4571.37 | C6: 4571.37 | D6: 4571.37 | E6: 4571.37 | F6: 4571.37 | G6: 4571.37 | H6: 4571.37
A7: 21 | B7: 1372.72 | C7: 1372.72 | D7: 1323.17 | E7: 1298.564 | F7: 1262.2828 | G7: 1262.2828 | H7: 1262.2828
A8: 22 | B8: 2171.48 | C8: 2171.48 | D8: 2151.842 | E8: 2151.842 | F8: 2124.232 | G8: 2095.722 | H8: 2079.178
A9: 23 | B9: 4632.05 | C9: 4632.05 | D9: 4632.05 | E9: 4632.05 | F9: 4632.05 | G9: 4568.13 | H9: 4500.46
A10: 24 | B10: 1319.75 | C10: 1319.75 | D10: 1319.75 | E10: 1319.75 | F10: 1319.75 | G10: 1319.75 | H10: 1319.75

Sheet HUS - Utilization evolution
A1: Utilization node | B1: Utilization capacity [Mt] | C1: 2030 utilization [Mt] | D1: 2035 utilization [Mt] | E1: 2040 utilization [Mt] | F1: 2045 utilization [Mt] | G1: 2050 utilization [Mt]
A2: 4 | B2: 225 | C2: 0 | D2: 65.417173 | E2: 158.41917 | F2: 164.46487 | G2: 197.06848
A3: 5 | B3: 112.5 | C3: 0 | D3: 0 | E3: 0 | F3: 26.413979 | G3: 112.5
A4: 6 | B4: 112.5 | C4: 0 | D4: 15.978827 | E4: 15.978827 | F4: 109.23065 | G4: 111.43065

Sheet HUS - Cost breakdown
A1: Concept | B1: 2030 | C1: 2035 | D1: 2040 | E1: 2045 | F1: 2050 | G1: Total
A2: Capture cost | B2: 5288.0388 | C2: 14008.748 | D2: 17012.929 | E2: 17547.226 | F2: 15726.985 | G2: 69583.927
A3: Injection cost | B3: 453.1814 | C3: 795.71296 | D3: 803.20604 | E3: 646.92863 | F3: 437.06628 | G3: 3136.0953
A4: CAPEX onshore pipe | B4: 677.888 | C4: 578.40807 | D4: 1387.6676 | E4: 406.61234 | F4: 476.97046 | G4: 3527.5465
A5: CAPEX onshore pipe (insulation only) | B5: 193.68229 | C5: 39.754385 | D5: 267.56703 | E5: 63.927725 | F5: 57.531404 | G5: 622.46283
A6: CAPEX offshore pipe | B6: 0 | C6: 98.422962 | D6: 66.686421 | E6: 0 | F6: 0 | G6: 165.10938
A7: CAPEX initial boosting stations | B7: 4983.8968 | C7: 9647.4559 | D7: 3694.8522 | E7: 3954.129 | F7: 1398.8621 | G7: 23679.196
A8: CAPEX additional boosting stations | B8: 0 | C8: 0 | D8: 549.47664 | E8: 87.736152 | F8: 249.93657 | G8: 887.14937
A9: OPEX onshore pipe | B9: 88.125663 | C9: 141.99271 | D9: 288.02749 | E9: 271.18378 | F9: 267.56553 | G9: 1056.8952
A10: OPEX onshore pipe (insulation only) | B10: 25.178761 | C10: 24.253647 | D10: 53.167988 | E10: 48.611528 | F10: 44.327492 | G10: 195.53942
A11: OPEX offshore pipe | B11: 0 | C11: 12.795014 | D11: 18.367903 | E11: 13.9229 | F11: 10.553524 | G11: 55.639341
A12: OPEX initial boosting stations | B12: 134.62097 | C12: 362.6964 | D12: 374.535 | E12: 390.5473 | F12: 333.82173 | G12: 1596.2214
A13: OPEX additional boosting stations | B13: 0 | C13: 0 | D13: 14.122674 | E13: 12.982308 | F13: 16.23514 | G13: 43.340122
... A19: TOTAL | B19: 57951.884 | C19: 46530.92 | D19: 29990.086 | E19: 19340.339 | F19: 8056.589 | G19: 161869.82

Sheet Network length per scenario
A1: Scenario | B1: 2030 | C1: 2035 | D1: 2040 | E1: 2045 | F1: 2050
A2: LUS | B2: 321.2 | C2: 688.95 | D2: 1089.57 | E2: 1380.47 | F2: 1952.92
A3: EUS | B3: 321.2 | C3: 606.45 | D3: 1080.3 | E3: 1829.3 | F3: 2574.13
A4: HUS | B4: 321.2 | C4: 757.8 | D4: 1718.79 | E4: 2146.06 | F4: 2763.79
