Workbook

Sheet LUS - Pipes
A1: Pipe ID | B1: Installed | C1: Diameter [inch] | D1: Distance until highest point [km] | E1: Longitude [km] | F1: Node connections | G1: Node types | H1: Initial pressure [bar] | I1: Pressure at highest point [bar] | J1: Final pressure [bar] | K1: Lowest pressure [bar] | L1: Initial temperature [°C] | M1: Temperature at critical pressure point [°C] | N1: Final temperature [°C] | O1: Lowest temperature [°C] | P1: Number of boosters | Q1: Booster installation year | R1: Installation Year | S1: Present Value Cost [M€] | T1: Insulated | U1: U-value [W/m^2/K] | V1: Insulation cost [M€] | W1: Booster delta pressure [bar] | X1: Booster delta temperature [°C] | Y1: Flow in 2030 | Z1: Flow in 2035 | AA1: Flow in 2040 | AB1: Flow in 2045 | AC1: Flow in 2050
A2: 17_a | B2: 0 | D2: 295.43 | E2: 336.49 | F2: (11, 25) | G2: ('E', 'A') | T2: FALSE
A3: 4_a | B3: 0 | D3: 99.73 | E3: 151.35 | F3: (6, 14) | G3: ('K', 'E') | T3: FALSE
A4: 49_a | B4: 0 | D4: 165.53 | E4: 302.06 | F4: (17, 25) | G4: ('E', 'A') | T4: FALSE
A5: 36_a | B5: 0 | D5: 77.08 | E5: 325.83 | F5: (10, 20) | G5: ('E', 'S') | T5: FALSE
A6: 63_a | B6: 0 | D6: 313.27 | E6: 447.89 | F6: (11, 17) | G6: ('E', 'E') | T6: FALSE
A7: 40_b | B7: 0 | D7: 209.77 | E7: 326.42 | F7: (21, 20) | G7: ('S', 'S') | T7: FALSE
A8: 59_a | B8: 0 | D8: 201.52 | E8: 356.04 | F8: (18, 20) | G8: ('E', 'S') | T8: FALSE
A9: 25_a | B9: 1 | C9: 38 | D9: 186.05 | E9: 297.08 | F9: (16, 27) | G9: ('E', 'A') | H9: 150 | I9: 83.176683 | J9: 238.75987 | K9: 83.176683 | L9: 25 | M9: 15.521725 | N9: 27.357529 | O9: 15.4939 | P9: 1 | Q9: 2045 | R9: 2045 | S9: 310.44075 | T9: FALSE | U9: 2 | V9: 0 | W9: 50 | X9: 10 | Y9: 0 | Z9: 0 | AA9: 0 | AB9: 107.39 | AC9: 110.85
A10: 37_b | B10: 0 | D10: 86.53 | E10: 347.61 | F10: (24, 5) | G10: ('S', 'K') | T10: FALSE
A11: 56_a | B11: 0 | D11: 41.05 | E11: 263.83 | F11: (15, 18) | G11: ('E', 'E') | T11: FALSE
A12: 31_a | B12: 1 | C12: 30 | D12: 85.68 | E12: 228.48 | F12: (15, 22) | G12: ('E', 'S') | H12: 150 | I12: 87.35104 | J12: 157.66753 | K12: 87.35104 | L12: 25 | M12: 18.302202 | N12: 25.322261 | O12: 15.341525 | P12: 1 | Q12: 2040 | R12: 2040 | S12: 250.32444 | T12: FALSE | U12: 2 | V12: 0 | W12: 50 | X12: 10 | Y12: 0 | Z12: 0 | AA12: 66.89 | AB12: 63.751372 | AC12: 73.04
A13: 58_a | B13: 0 | D13: 164.64 | E13: 189.66 | F13: (4, 24) | G13: ('K', 'S') | T13: FALSE
A14: 31_b | B14: 0 | D14: 142.8 | E14: 228.48 | F14: (22, 15) | G14: ('S', 'E') | T14: FALSE
A15: 23_a | B15: 0 | D15: 38.1 | E15: 179.47 | F15: (14, 21) | G15: ('E', 'S') | T15: FALSE
A16: 44_b | B16: 0 | D16: 258.27 | E16: 348.87 | F16: (23, 12) | G16: ('S', 'E') | T16: FALSE
A17: 43_a | B17: 0 | D17: 148.58 | E17: 370.19 | F17: (14, 17) | G17: ('E', 'E') | T17: FALSE
A18: 29_b | B18: 1 | C18: 18 | D18: 0 | E18: 78.12 | F18: (12, 5) | G18: ('E', 'K') | H18: 150 | I18: 150 | J18: 182.827 | K18: 150 | L18: 25 | M18: 25 | N18: 18.083504 | O18: 18.10041 | P18: 0 | R18: 2030 | S18: 99.69535 | T18: FALSE | U18: 2 | V18: 0 | Y18: 14.468 | Z18: 19.282 | AA18: 25.8 | AB18: 26.413979 | AC18: 26.413979
A19: 13_b | B19: 1 | C19: 34 | D19: 183.25 | E19: 343.97 | F19: (22, 20) | G19: ('S', 'S') | H19: 178.00921 | I19: 72.949938 | J19: 195.23118 | K19: 72.949938 | L19: 25.086203 | M19: 12.702641 | N19: 22.227783 | O19: 12.206166 | P19: 1 | Q19: 2050 | R19: 2050 | S19: 244.00848 | T19: FALSE | U19: 2 | V19: 0 | W19: 50 | X19: 10 | Y19: 0 | Z19: 0 | AA19: 0 | AB19: 0 | AC19: 0
A20: 43_b | B20: 0 | D20: 221.62 | E20: 370.19 | F20: (17, 14) | G20: ('E', 'E') | T20: FALSE
A21: 67_b | B21: 0 | D21: 85.34 | E21: 110.44 | F21: (26, 11) | G21: ('A', 'E') | T21: FALSE
A22: 51_a | B22: 0 | D22: 290.25 | E22: 463.4 | F22: (4, 12) | G22: ('K', 'E') | T22: FALSE
A23: 51_b | B23: 0 | D23: 173.15 | E23: 463.4 | F23: (12, 4) | G23: ('E', 'K') | T23: FALSE
A24: 3_b | B24: 1 | C24: 34 | D24: 57.79 | E24: 68.85 | F24: (17, 4) | G24: ('E', 'K') | H24: 150 | I24: 137.47836 | J24: 143.33677 | K24: 137.47836 | L24: 25 | M24: 21.998053 | N24: 21.839455 | O24: 21.759017 | P24: 0 | R24: 2035 | S24: 107.77334 | T24: FALSE | U24: 2 | V24: 0 | Y24: 0 | Z24: 27.132 | AA24: 60.486 | AB24: 74.21 | AC24: 75
A25: 14_a | B25: 1 | C25: 26 | D25: 147.03 | E25: 222.05 | F25: (10, 21) | G25: ('E', 'S') | H25: 150 | I25: 68.230718 | J25: 136.22208 | K25: 68.230718 | L25: 25 | M25: 14.398163 | N25: 23.788198 | O25: 13.25316 | P25: 1 | Q25: 2040 | R25: 2040 | S25: 210.84234 | T25: FALSE | U25: 2 | V25: 0 | W25: 50 | X25: 10 | Y25: 0 | Z25: 0 | AA25: 44.74 | AB25: 55.110648 | AC25: 55.110648
A26: 37_a | B26: 0 | D26: 261.08 | E26: 347.61 | F26: (5, 24) | G26: ('K', 'S') | T26: FALSE
A27: 3_a | B27: 0 | D27: 11.06 | E27: 68.85 | F27: (4, 17) | G27: ('K', 'E') | T27: FALSE
A28: 58_b | B28: 0 | D28: 25.02 | E28: 189.66 | F28: (24, 4) | G28: ('S', 'K') | T28: FALSE
A29: 28_b | B29: 0 | D29: 288.59 | E29: 496.16 | F29: (16, 13) | G29: ('E', 'E') | T29: FALSE
A30: 67_a | B30: 1 | C30: 42 | D30: 12.05 | E30: 110.44 | F30: (11, 26) | G30: ('E', 'A') | H30: 150 | I30: 104.45679 | J30: 153.46191 | K30: 104.45679 | L30: 25 | M30: 22.20149 | N30: 22.189588 | O30: 22.206751 | P30: 0 | R30: 2035 | S30: 216.29825 | T30: FALSE | U30: 2 | V30: 0 | Y30: 0 | Z30: 135.82 | AA30: 131.33 | AB30: 128.46 | AC30: 127.07
A31: 44_a | B31: 0 | D31: 90.6 | E31: 348.87 | F31: (12, 23) | G31: ('E', 'S') | T31: FALSE
A32: 34_b | B32: 0 | D32: 200.08 | E32: 553.72 | F32: (12, 11) | G32: ('E', 'E') | T32: FALSE
A33: 32_a | B33: 0 | D33: 303.66 | E33: 345.18 | F33: (5, 21) | G33: ('K', 'S') | T33: FALSE
A34: 64_a | B34: 0 | D34: 222.05 | E34: 245.06 | F34: (17, 24) | G34: ('E', 'S') | T34: FALSE
A35: 61_a | B35: 0 | D35: 229.52 | E35: 233.52 | F35: (18, 23) | G35: ('E', 'S') | T35: FALSE
A36: 62_b | B36: 0 | D36: 61.67 | E36: 147.41 | F36: (22, 10) | G36: ('S', 'E') | T36: FALSE
A37: 4_b | B37: 1 | C37: 38 | D37: 51.62 | E37: 151.35 | F37: (14, 6) | G37: ('E', 'K') | H37: 150 | I37: 100.14645 | J37: 205.93858 | K37: 100.14645 | L37: 25 | M37: 20.372963 | N37: 21.169234 | O37: 20.653032 | P37: 0 | R37: 2050 | S37: 117.48797 | T37: FALSE | U37: 2 | V37: 0 | Y37: 0 | Z37: 0 | AA37: 0 | AB37: 0 | AC37: 56.32
A38: 16_a | B38: 0 | D38: 30.51 | E38: 555.74 | F38: (12, 27) | G38: ('E', 'A') | T38: FALSE
A39: 5_b | B39: 0 | D39: 14.54 | E39: 80.23 | F39: (23, 13) | G39: ('S', 'E') | T39: FALSE
A40: 54_a | B40: 1 | C40: 18 | D40: 37.23 | E40: 45.28 | F40: (5, 20) | G40: ('K', 'S') | H40: 182.827 | I40: 165.79097 | J40: 166.05856 | K40: 165.79097 | L40: 18.083504 | M40: 16.497934 | N40: 16.317469 | O40: 16.359963 | P40: 0 | R40: 2030 | S40: 81.477722 | T40: TRUE | U40: 0.43 | V40: 30.554146 | Y40: 14.468 | Z40: 19.282 | AA40: 25.8 | AB40: 0.58747932 | AC40: 0
A41: 2_b | B41: 0 | D41: 328.74 | E41: 448.83 | F41: (11, 4) | G41: ('E', 'K') | T41: FALSE
A42: 60_b | B42: 1 | C42: 6 | D42: 42.53 | E42: 127.1 | F42: (21, 6) | G42: ('S', 'K') | H42: 136.22208 | I42: 82.660058 | J42: 181.60425 | K42: 82.660058 | L42: 23.788198 | M42: 13.299066 | N42: 20.768597 | O42: 10.693933 | P42: 1 | Q42: 2050 | R42: 2050 | S42: 16.689442 | T42: FALSE | U42: 2 | V42: 0 | W42: 50 | X42: 10 | Y42: 0 | Z42: 0 | AA42: 0 | AB42: 0 | AC42: 0
A43: 59_b | B43: 0 | D43: 154.52 | E43: 356.04 | F43: (20, 18) | G43: ('S', 'E') | T43: FALSE
A44: 50_a | B44: 0 | D44: 229 | E44: 561.51 | F44: (13, 15) | G44: ('E', 'E') | T44: FALSE
A45: 70_b | B45: 0 | D45: 305.38 | E45: 369.46 | F45: (19, 16) | G45: ('S', 'E') | T45: FALSE
A46: 30_b | B46: 0 | D46: 199.06 | E46: 243.08 | F46: (19, 13) | G46: ('S', 'E') | T46: FALSE
A47: 0_a | B47: 0 | D47: 302.33 | E47: 423.46 | F47: (4, 5) | G47: ('K', 'K') | T47: FALSE
A48: 34_a | B48: 0 | D48: 353.64 | E48: 553.72 | F48: (11, 12) | G48: ('E', 'E') | T48: FALSE
A49: 7_b | B49: 0 | D49: 167.02 | E49: 518.06 | F49: (17, 6) | G49: ('E', 'K') | T49: FALSE
A50: 29_a | B50: 0 | D50: 78.12 | E50: 78.12 | F50: (5, 12) | G50: ('K', 'E') | T50: FALSE
A51: 10_b | B51: 0 | D51: 132.71 | E51: 141.73 | F51: (22, 18) | G51: ('S', 'E') | T51: FALSE
A52: 2_a | B52: 0 | D52: 120.09 | E52: 448.83 | F52: (4, 11) | G52: ('K', 'E') | T52: FALSE
A53: 68_a | B53: 0 | D53: 29.03 | E53: 189.69 | F53: (12, 19) | G53: ('E', 'S') | T53: FALSE
A54: 1_a | B54: 0 | D54: 350.21 | E54: 491.3 | F54: (19, 27) | G54: ('S', 'A') | T54: FALSE
... A60: 16_b | B60: 0 | D60: 524.22 | E60: 555.74 | F60: (27, 12) | G60: ('A', 'E') | T60: FALSE
A61: 60_a | B61: 1 | C61: 18 | D61: 84.57 | E61: 127.1 | F61: (6, 21) | G61: ('K', 'S') | H61: 181.60425 | I61: 86.861867 | J61: 164.28217 | K61: 86.861867 | L61: 20.768597 | M61: 10.808953 | N61: 20.565076 | O61: 10.22278 | P61: 1 | Q61: 2050 | R61: 2050 | S61: 50.501334 | T61: FALSE | U61: 2 | V61: 0 | W61: 50 | X61: 10 | Y61: 0 | Z61: 0 | AA61: 0 | AB61: 0 | AC61: 18.82
A62: 65_a | B62: 0 | D62: 268.79 | E62: 361.88 | F62: (20, 23) | G62: ('S', 'S') | T62: FALSE
A63: 65_b | B63: 0 | D63: 93.1 | E63: 361.88 | F63: (23, 20) | G63: ('S', 'S') | T63: FALSE
A64: 57_b | B64: 0 | D64: 85.12 | E64: 166.23 | F64: (28, 21) | G64: ('A', 'S') | T64: FALSE
A65: 56_b | B65: 0 | D65: 222.78 | E65: 263.83 | F65: (18, 15) | G65: ('E', 'E') | T65: FALSE
A66: 19_a | B66: 0 | D66: 55.08 | E66: 130.7 | F66: (14, 24) | G66: ('E', 'S') | T66: FALSE
A67: 36_b | B67: 0 | D67: 248.75 | E67: 325.83 | F67: (20, 10) | G67: ('S', 'E') | T67: FALSE
A68: 68_b | B68: 0 | D68: 160.66 | E68: 189.69 | F68: (19, 12) | G68: ('S', 'E') | T68: FALSE
A69: 23_b | B69: 0 | D69: 141.37 | E69: 179.47 | F69: (21, 14) | G69: ('S', 'E') | T69: FALSE
A70: 19_b | B70: 0 | D70: 75.61 | E70: 130.7 | F70: (24, 14) | G70: ('S', 'E') | T70: FALSE
A71: 53_b | B71: 0 | D71: 32.04 | E71: 371.42 | F71: (14, 5) | G71: ('E', 'K') | T71: FALSE
A72: 40_a | B72: 0 | D72: 116.65 | E72: 326.42 | F72: (20, 21) | G72: ('S', 'S') | T72: FALSE
A73: 7_a | B73: 0 | D73: 351.04 | E73: 518.06 | F73: (6, 17) | G73: ('K', 'E') | T73: FALSE
... A81: 9_b | B81: 0 | D81: 2.5 | E81: 484.78 | F81: (23, 15) | G81: ('S', 'E') | T81: FALSE
A82: 41_a | B82: 1 | C82: 6 | D82: 0 | E82: 100.6 | F82: (12, 20) | G82: ('E', 'S') | H82: 150 | I82: 135.08749 | J82: 186.57914 | K82: 135.08749 | L82: 25 | M82: 7.6853824 | N82: 17.454017 | O82: 7.4880925 | P82: 1 | Q82: 2050 | R82: 2050 | S82: 13.351023 | T82: FALSE | U82: 2 | V82: 0 | W82: 50 | X82: 10 | Y82: 0 | Z82: 0 | AA82: 0 | AB82: 0 | AC82: 1.7860207
A83: 10_a | B83: 1 | C83: 22 | D83: 9.01 | E83: 141.73 | F83: (18, 22) | G83: ('E', 'S') | H83: 150 | I83: 127.59719 | J83: 178.00921 | K83: 127.59719 | L83: 25 | M83: 23.135811 | N83: 25.086203 | O83: 15.119394 | P83: 1 | Q83: 2045 | R83: 2045 | S83: 83.786518 | T83: FALSE | U83: 2 | V83: 0 | W83: 50 | X83: 10 | Y83: 0 | Z83: 0 | AA83: 0 | AB83: 0 | AC83: 29.59
A84: 47_b | B84: 0 | D84: 530.62 | E84: 562.63 | F84: (26, 12) | G84: ('A', 'E') | T84: FALSE
A85: 0_b | B85: 0 | D85: 121.13 | E85: 423.46 | F85: (5, 4) | G85: ('K', 'K') | T85: FALSE
A86: 54_b | B86: 1 | C86: 10 | D86: 8.05 | E86: 45.28 | F86: (20, 5) | G86: ('S', 'K') | H86: 195.23118 | I86: 191.04354 | J86: 194.88213 | K86: 191.04354 | L86: 22.227783 | M86: 20.942764 | N86: 20.373035 | O86: 20.405712 | P86: 0 | R86: 2050 | S86: 14.871588 | T86: TRUE | U86: 0.43 | V86: 5.5768456 | Y86: 0 | Z86: 0 | AA86: 0 | AB86: 0 | AC86: 1.4581689
A87: 47_a | B87: 0 | D87: 31.51 | E87: 562.63 | F87: (12, 26) | G87: ('E', 'A') | T87: FALSE
A88: 13_a | B88: 0 | D88: 160.72 | E88: 343.97 | F88: (20, 22) | G88: ('S', 'S') | T88: FALSE
A89: 28_a | B89: 0 | D89: 207.57 | E89: 496.16 | F89: (13, 16) | G89: ('E', 'E') | T89: FALSE
A90: 62_a | B90: 0 | D90: 85.74 | E90: 147.41 | F90: (10, 22) | G90: ('E', 'S') | T90: FALSE
A91: 17_b | B91: 0 | D91: 40.56 | E91: 336.49 | F91: (25, 11) | G91: ('A', 'E') | T91: FALSE
A92: 5_a | B92: 1 | C92: 30 | D92: 65.69 | E92: 80.23 | F92: (13, 23) | G92: ('E', 'S') | H92: 150 | I92: 108.84972 | J92: 142.61203 | K92: 108.84972 | L92: 25 | M92: 19.979067 | N92: 20.615835 | O92: 19.584348 | P92: 0 | R92: 2030 | S92: 151.97322 | T92: FALSE | U92: 2 | V92: 0 | Y92: 54.72 | Z92: 57.46 | AA92: 60.52 | AB92: 63.92 | AC92: 67.67
A93: 32_b | B93: 0 | D93: 41.52 | E93: 345.18 | F93: (21, 5) | G93: ('S', 'K') | T93: FALSE
A94: 49_b | B94: 0 | D94: 48.51 | E94: 302.06 | F94: (25, 17) | G94: ('A', 'E') | T94: FALSE
A95: 25_b | B95: 0 | D95: 109.53 | E95: 297.08 | F95: (27, 16) | G95: ('A', 'E') | T95: FALSE
A96: 9_a | B96: 0 | D96: 482.28 | E96: 484.78 | F96: (15, 23) | G96: ('E', 'S') | T96: FALSE
A97: 53_a | B97: 0 | D97: 339.39 | E97: 371.42 | F97: (5, 14) | G97: ('K', 'E') | T97: FALSE
A98: 18_a | B98: 0 | D98: 0 | E98: 135.33 | F98: (9, 28) | G98: ('E', 'A')
A99: 71_a | B99: 0 | D99: 0 | E99: 192.08 | F99: (8, 9) | G99: ('E', 'E')
A100: 52_a | B100: 0 | D100: 0 | E100: 25.73 | F100: (2, 26) | G100: ('S', 'A')
A101: 71_b | B101: 0 | D101: 0 | E101: 192.08 | F101: (9, 8) | G101: ('E', 'E')
A102: 11_a | B102: 0 | D102: 0 | E102: 24.61 | F102: (1, 25) | G102: ('S', 'A')
A103: 20_b | B103: 1 | C103: 38 | D103: 0 | E103: 25.42 | F103: (27, 3) | G103: ('A', 'S') | H103: 238.75987 | J103: 236.95987 | K103: 236.95987 | L103: 27.357529 | N103: 15 | P103: 0 | R103: 2045 | S103: 50.548483 | V103: 0 | Y103: 0 | Z103: 0 | AA103: 0 | AB103: 107.39 | AC103: 110.85
A104: 46_b | B104: 0 | D104: 0 | E104: 161.79 | F104: (8, 7) | G104: ('E', 'E')
A105: 18_b | B105: 0 | D105: 0 | E105: 135.33 | F105: (28, 9) | G105: ('A', 'E')
A106: 20_a | B106: 0 | D106: 0 | E106: 25.42 | F106: (3, 27) | G106: ('S', 'A')
A107: 11_b | B107: 0 | D107: 0 | E107: 24.61 | F107: (25, 1) | G107: ('A', 'S')
A108: 52_b | B108: 1 | C108: 42 | D108: 0 | E108: 25.73 | F108: (26, 2) | G108: ('A', 'S') | H108: 153.46191 | J108: 151.84191 | K108: 151.84191 | L108: 22.189588 | N108: 15 | P108: 0 | R108: 2035 | S108: 98.422962 | V108: 0 | Y108: 0 | Z108: 135.82 | AA108: 131.33 | AB108: 128.46 | AC108: 127.07
A109: 46_a | B109: 0 | D109: 0 | E109: 161.79 | F109: (7, 8) | G109: ('E', 'E')

Sheet LUS - Sinks capacity evolution
A1: Sink node | B1: Initial capacity [Mt] | C1: 2030 capacity [Mt] | D1: 2035 capacity [Mt] | E1: 2040 capacity [Mt] | F1: 2045 capacity [Mt] | G1: 2050 capacity [Mt] | H1: Final capacity [Mt]
A2: 1 | B2: 1250 | C2: 1250 | D2: 1250 | E2: 1250 | F2: 1250 | G2: 1250 | H2: 1250
A3: 2 | B3: 3790 | C3: 3790 | D3: 3790 | E3: 3654.18 | F3: 3522.85 | G3: 3394.39 | H3: 3267.32
A4: 3 | B4: 2100 | C4: 2100 | D4: 2100 | E4: 2100 | F4: 2100 | G4: 1992.61 | H4: 1881.76
A5: 19 | B5: 6655.37 | C5: 6655.37 | D5: 6655.37 | E5: 6655.37 | F5: 6655.37 | G5: 6655.37 | H5: 6655.37
A6: 20 | B6: 4571.37 | C6: 4571.37 | D6: 4556.902 | E6: 4537.62 | F6: 4511.82 | G6: 4511.2325 | H6: 4510.9047
A7: 21 | B7: 1372.72 | C7: 1372.72 | D7: 1372.72 | E7: 1372.72 | F7: 1327.98 | G7: 1272.8694 | H7: 1198.9387
A8: 22 | B8: 2171.48 | C8: 2171.48 | D8: 2171.48 | E8: 2171.48 | F8: 2104.59 | G8: 2040.8386 | H8: 1938.2086
A9: 23 | B9: 4632.05 | C9: 4632.05 | D9: 4577.33 | E9: 4519.87 | F9: 4459.35 | G9: 4395.43 | H9: 4327.76
A10: 24 | B10: 1319.75 | C10: 1319.75 | D10: 1319.75 | E10: 1319.75 | F10: 1319.75 | G10: 1319.75 | H10: 1319.75

Sheet LUS - Utilization evolution
A1: Utilization node | B1: Utilization capacity [Mt] | C1: 2030 utilization [Mt] | D1: 2035 utilization [Mt] | E1: 2040 utilization [Mt] | F1: 2045 utilization [Mt] | G1: 2050 utilization [Mt]
A2: 4 | B2: 75 | C2: 0 | D2: 27.132 | E2: 60.486 | F2: 74.21 | G2: 75
A3: 5 | B3: 37.5 | C3: 0 | D3: 0 | E3: 0 | F3: 25.8265 | G3: 27.872148
A4: 6 | B4: 37.5 | C4: 0 | D4: 0 | E4: 0 | F4: 0 | G4: 37.5

Sheet LUS - Cost breakdown
A1: Concept | B1: 2030 | C1: 2035 | D1: 2040 | E1: 2045 | F1: 2050 | G1: Total
A2: Capture cost | B2: 5288.0388 | C2: 13885.473 | D2: 17114.625 | E2: 17286.032 | F2: 15714.522 | G2: 69288.691
A3: Injection cost | B3: 453.1814 | C3: 1054.3075 | D3: 1241.3856 | E3: 1194.7756 | F3: 1042.1536 | G3: 4985.8037
A4: CAPEX onshore pipe | B4: 333.14629 | C4: 324.07159 | D4: 461.16678 | E4: 394.22726 | F4: 456.90984 | G4: 1969.5218
A5: CAPEX onshore pipe (insulation only) | B5: 30.554146 | C5: 0 | D5: 0 | E5: 0 | F5: 5.5768456 | G5: 36.130991
A6: CAPEX offshore pipe | B6: 0 | C6: 98.422962 | D6: 0 | E6: 50.548483 | F6: 0 | G6: 148.97145
A7: CAPEX initial boosting stations | B7: 5561.7063 | C7: 9647.4559 | D7: 4455.4884 | E7: 2800.7361 | F7: 1645.3483 | G7: 24110.735
A8: CAPEX additional boosting stations | B8: 0 | C8: 0 | D8: 269.94239 | E8: 250.22974 | F8: 152.71715 | G8: 672.88928
A9: OPEX onshore pipe | B9: 43.309138 | C9: 74.957841 | D9: 116.76958 | E9: 139.76126 | F9: 165.33782 | G9: 540.13563
A10: OPEX onshore pipe (insulation only) | B10: 3.9720485 | C10: 3.010823 | D10: 2.282275 | E10: 1.7298952 | F10: 2.0363469 | G10: 13.031389
A11: OPEX offshore pipe | B11: 0 | C11: 12.795014 | D11: 9.6986662 | E11: 13.9229 | F11: 10.553524 | G11: 46.970104
A12: OPEX initial boosting stations | B12: 150.22829 | C12: 374.52888 | D12: 404.037 | E12: 381.76996 | F12: 333.82173 | G12: 1644.3859
A13: OPEX additional boosting stations | B13: 0 | C13: 0 | D13: 6.9380719 | E13: 11.712154 | F13: 12.777844 | G13: 31.42807
... A19: TOTAL | B19: 58155.742 | C19: 50788.49 | D19: 36521.376 | E19: 28204.247 | F19: 18339.501 | G19: 192009.36

Sheet EUS - Pipes
A1: Pipe ID | B1: Length [km] | C1: Installed | D1: Diameter [inch] | E1: Distance until highest point [km] | F1: Longitude [km] | G1: Node connections | H1: Node types | I1: Initial pressure [bar] | J1: Pressure at highest point [bar] | K1: Final pressure [bar] | L1: Lowest pressure [bar] | M1: Initial temperature [°C] | N1: Temperature at critical pressure point [°C] | O1: Final temperature [°C] | P1: Lowest temperature [°C] | Q1: Number of boosters | R1: Booster installation year | S1: Installation Year | T1: Present Value Cost [M€] | U1: Insulated | V1: U-value [W/m^2/K] | W1: Insulation cost [M€] | X1: Booster delta pressure [bar] | Y1: Booster delta temperature [°C] | Z1: Flow in 2030 | AA1: Flow in 2035 | AB1: Flow in 2040 | AC1: Flow in 2045 | AD1: Flow in 2050
A2: 17_a | B2: =VLOOKUP(A2,PIPE!A:D,4,0) -> 336.49 | C2: 0 | E2: 295.43 | F2: 336.49 | G2: (11, 25) | H2: ('E', 'A') | U2: FALSE
A3: 4_a | B3: =VLOOKUP(A3,PIPE!A:D,4,0) -> 151.35 | C3: 0 | E3: 99.73 | F3: 151.35 | G3: (6, 14) | H3: ('K', 'E') | U3: FALSE
A4: 49_a | B4: =VLOOKUP(A4,PIPE!A:D,4,0) -> 302.06 | C4: 0 | E4: 165.53 | F4: 302.06 | G4: (17, 25) | H4: ('E', 'A') | U4: FALSE
A5: 36_a | B5: =VLOOKUP(A5,PIPE!A:D,4,0) -> 325.83 | C5: 0 | E5: 77.08 | F5: 325.83 | G5: (10, 20) | H5: ('E', 'S') | U5: FALSE
A6: 63_a | B6: =VLOOKUP(A6,PIPE!A:D,4,0) -> 447.89 | C6: 0 | E6: 313.27 | F6: 447.89 | G6: (11, 17) | H6: ('E', 'E') | U6: FALSE
A7: 40_b | B7: =VLOOKUP(A7,PIPE!A:D,4,0) -> 326.42 | C7: 0 | E7: 209.77 | F7: 326.42 | G7: (21, 20) | H7: ('S', 'S') | U7: FALSE
A8: 59_a | B8: =VLOOKUP(A8,PIPE!A:D,4,0) -> 356.04 | C8: 0 | E8: 201.52 | F8: 356.04 | G8: (18, 20) | H8: ('E', 'S') | U8: FALSE
A9: 25_a | B9: =VLOOKUP(A9,PIPE!A:D,4,0) -> 297.08 | C9: 1 | D9: 38 | E9: 186.05 | F9: 297.08 | G9: (16, 27) | H9: ('E', 'A') | I9: 150 | J9: 83.176683 | K9: 238.75987 | L9: 83.176683 | M9: 25 | N9: 15.521725 | O9: 27.357529 | P9: 15.4939 | Q9: 1 | R9: 2045 | S9: 2045 | T9: 310.44075 | U9: FALSE | V9: 2 | W9: 0 | X9: 50 | Y9: 10 | Z9: 0 | AA9: 0 | AB9: 0 | AC9: 106.29502 | AD9: 110.85
A10: 37_b | B10: =VLOOKUP(A10,PIPE!A:D,4,0) -> 347.61 | C10: 0 | E10: 86.53 | F10: 347.61 | G10: (24, 5) | H10: ('S', 'K') | U10: FALSE
A11: 56_a | B11: =VLOOKUP(A11,PIPE!A:D,4,0) -> 263.83 | C11: 0 | E11: 41.05 | F11: 263.83 | G11: (15, 18) | H11: ('E', 'E') | U11: FALSE
A12: 31_a | B12: =VLOOKUP(A12,PIPE!A:D,4,0) -> 228.48 | C12: 1 | D12: 30 | E12: 85.68 | F12: 228.48 | G12: (15, 22) | H12: ('E', 'S') | I12: 150 | J12: 87.35104 | K12: 157.66753 | L12: 87.35104 | M12: 25 | N12: 18.302202 | O12: 25.322261 | P12: 15.341525 | Q12: 1 | R12: 2040 | S12: 2040 | T12: 250.32444 | U12: FALSE | V12: 2 | W12: 0 | X12: 50 | Y12: 10 | Z12: 0 | AA12: 0 | AB12: 53.516 | AC12: 69.76 | AD12: 72.712
A13: 58_a | B13: =VLOOKUP(A13,PIPE!A:D,4,0) -> 189.66 | C13: 0 | E13: 164.64 | F13: 189.66 | G13: (4, 24) | H13: ('K', 'S') | U13: FALSE
A14: 31_b | B14: =VLOOKUP(A14,PIPE!A:D,4,0) -> 228.48 | C14: 0 | E14: 142.8 | F14: 228.48 | G14: (22, 15) | H14: ('S', 'E') | U14: FALSE
A15: 23_a | B15: =VLOOKUP(A15,PIPE!A:D,4,0) -> 179.47 | C15: 0 | E15: 38.1 | F15: 179.47 | G15: (14, 21) | H15: ('E', 'S') | U15: FALSE
A16: 44_b | B16: =VLOOKUP(A16,PIPE!A:D,4,0) -> 348.87 | C16: 0 | E16: 258.27 | F16: 348.87 | G16: (23, 12) | H16: ('S', 'E') | U16: FALSE
A17: 43_a | B17: =VLOOKUP(A17,PIPE!A:D,4,0) -> 370.19 | C17: 0 | E17: 148.58 | F17: 370.19 | G17: (14, 17) | H17: ('E', 'E') | U17: FALSE
A18: 29_b | B18: =VLOOKUP(A18,PIPE!A:D,4,0) -> 78.12 | C18: 1 | D18: 18 | E18: 0 | F18: 78.12 | G18: (12, 5) | H18: ('E', 'K') | I18: 150 | J18: 150 | K18: 182.827 | L18: 150 | M18: 25 | N18: 25 | O18: 18.083504 | P18: 18.10041 | Q18: 0 | S18: 2030 | T18: 99.69535 | U18: FALSE | V18: 2 | W18: 0 | Z18: 14.468 | AA18: 24.83 | AB18: 25.8 | AC18: 26.413979 | AD18: 26.413979
A19: 13_b | B19: =VLOOKUP(A19,PIPE!A:D,4,0) -> 343.97 | C19: 1 | D19: 34 | E19: 183.25 | F19: 343.97 | G19: (22, 20) | H19: ('S', 'S') | I19: 178.00921 | J19: 72.949938 | K19: 195.23118 | L19: 72.949938 | M19: 25.086203 | N19: 12.702641 | O19: 22.227783 | P19: 12.206166 | Q19: 1 | R19: 2050 | S19: 2050 | T19: 244.00848 | U19: FALSE | V19: 2 | W19: 0 | X19: 50 | Y19: 10 | Z19: 0 | AA19: 0 | AB19: 0 | AC19: 0 | AD19: 46.8
A20: 43_b | B20: =VLOOKUP(A20,PIPE!A:D,4,0) -> 370.19 | C20: 0 | E20: 221.62 | F20: 370.19 | G20: (17, 14) | H20: ('E', 'E') | U20: FALSE
A21: 67_b | B21: =VLOOKUP(A21,PIPE!A:D,4,0) -> 110.44 | C21: 0 | E21: 85.34 | F21: 110.44 | G21: (26, 11) | H21: ('A', 'E') | U21: FALSE
A22: 51_a | B22: =VLOOKUP(A22,PIPE!A:D,4,0) -> 463.4 | C22: 0 | E22: 290.25 | F22: 463.4 | G22: (4, 12) | H22: ('K', 'E') | U22: FALSE
A23: 51_b | B23: =VLOOKUP(A23,PIPE!A:D,4,0) -> 463.4 | C23: 0 | E23: 173.15 | F23: 463.4 | G23: (12, 4) | H23: ('E', 'K') | U23: FALSE
A24: 3_b | B24: =VLOOKUP(A24,PIPE!A:D,4,0) -> 68.85 | C24: 1 | D24: 34 | E24: 57.79 | F24: 68.85 | G24: (17, 4) | H24: ('E', 'K') | I24: 150 | J24: 137.47836 | K24: 143.33677 | L24: 137.47836 | M24: 25 | N24: 21.998053 | O24: 21.839455 | P24: 21.759017 | Q24: 0 | S24: 2040 | T24: 81.692508 | U24: FALSE | V24: 2 | W24: 0 | Z24: 0 | AA24: 0 | AB24: 71.61 | AC24: 74.21 | AD24: 77.28
A25: 14_a | B25: =VLOOKUP(A25,PIPE!A:D,4,0) -> 222.05 | C25: 1 | D25: 26 | E25: 147.03 | F25: 222.05 | G25: (10, 21) | H25: ('E', 'S') | I25: 150 | J25: 68.230718 | K25: 136.22208 | L25: 68.230718 | M25: 25 | N25: 14.398163 | O25: 23.788198 | P25: 13.25316 | Q25: 1 | R25: 2040 | S25: 2040 | T25: 210.84234 | U25: FALSE | V25: 2 | W25: 0 | X25: 50 | Y25: 10 | Z25: 0 | AA25: 0 | AB25: 0 | AC25: 0 | AD25: 55.110648
A26: 37_a | B26: =VLOOKUP(A26,PIPE!A:D,4,0) -> 347.61 | C26: 0 | E26: 261.08 | F26: 347.61 | G26: (5, 24) | H26: ('K', 'S') | U26: FALSE
A27: 3_a | B27: =VLOOKUP(A27,PIPE!A:D,4,0) -> 68.85 | C27: 0 | E27: 11.06 | F27: 68.85 | G27: (4, 17) | H27: ('K', 'E') | U27: FALSE
A28: 58_b | B28: =VLOOKUP(A28,PIPE!A:D,4,0) -> 189.66 | C28: 0 | E28: 25.02 | F28: 189.66 | G28: (24, 4) | H28: ('S', 'K') | U28: FALSE
A29: 28_b | B29: =VLOOKUP(A29,PIPE!A:D,4,0) -> 496.16 | C29: 0 | E29: 288.59 | F29: 496.16 | G29: (16, 13) | H29: ('E', 'E') | U29: FALSE
A30: 67_a | B30: =VLOOKUP(A30,PIPE!A:D,4,0) -> 110.44 | C30: 1 | D30: 42 | E30: 12.05 | F30: 110.44 | G30: (11, 26) | H30: ('E', 'A') | I30: 150 | J30: 104.45679 | K30: 153.46191 | L30: 104.45679 | M30: 25 | N30: 22.20149 | O30: 22.189588 | P30: 22.206751 | Q30: 0 | S30: 2035 | T30: 216.29825 | U30: FALSE | V30: 2 | W30: 0 | Z30: 0 | AA30: 107.738 | AB30: 131.33 | AC30: 83.130979 | AD30: 71.959352
A31: 44_a | B31: =VLOOKUP(A31,PIPE!A:D,4,0) -> 348.87 | C31: 0 | E31: 90.6 | F31: 348.87 | G31: (12, 23) | H31: ('E', 'S') | U31: FALSE
A32: 34_b | B32: =VLOOKUP(A32,PIPE!A:D,4,0) -> 553.72 | C32: 0 | E32: 200.08 | F32: 553.72 | G32: (12, 11) | H32: ('E', 'E') | U32: FALSE
A33: 32_a | B33: =VLOOKUP(A33,PIPE!A:D,4,0) -> 345.18 | C33: 0 | E33: 303.66 | F33: 345.18 | G33: (5, 21) | H33: ('K', 'S') | U33: FALSE
A34: 64_a | B34: =VLOOKUP(A34,PIPE!A:D,4,0) -> 245.06 | C34: 0 | E34: 222.05 | F34: 245.06 | G34: (17, 24) | H34: ('E', 'S') | U34: FALSE
A35: 61_a | B35: =VLOOKUP(A35,PIPE!A:D,4,0) -> 233.52 | C35: 0 | E35: 229.52 | F35: 233.52 | G35: (18, 23) | H35: ('E', 'S') | U35: FALSE
A36: 62_b | B36: =VLOOKUP(A36,PIPE!A:D,4,0) -> 147.41 | C36: 0 | E36: 61.67 | F36: 147.41 | G36: (22, 10) | H36: ('S', 'E') | U36: FALSE
A37: 4_b | B37: =VLOOKUP(A37,PIPE!A:D,4,0) -> 151.35 | C37: 1 | D37: 38 | E37: 51.62 | F37: 151.35 | G37: (14, 6) | H37: ('E', 'K') | I37: 150 | J37: 100.14645 | K37: 205.93858 | L37: 100.14645 | M37: 25 | N37: 20.372963 | O37: 21.169234 | P37: 20.653032 | Q37: 0 | S37: 2035 | T37: 269.76181 | U37: FALSE | V37: 2 | W37: 0 | Z37: 0 | AA37: 50.73 | AB37: 49.362 | AC37: 54.12 | AD37: 56.32
A38: 16_a | B38: =VLOOKUP(A38,PIPE!A:D,4,0) -> 555.74 | C38: 0 | E38: 30.51 | F38: 555.74 | G38: (12, 27) | H38: ('E', 'A') | U38: FALSE
A39: 5_b | B39: =VLOOKUP(A39,PIPE!A:D,4,0) -> 80.23 | C39: 0 | E39: 14.54 | F39: 80.23 | G39: (23, 13) | H39: ('S', 'E') | U39: FALSE
A40: 54_a | B40: =VLOOKUP(A40,PIPE!A:D,4,0) -> 45.28 | C40: 1 | D40: 18 | E40: 37.23 | F40: 45.28 | G40: (5, 20) | H40: ('K', 'S') | I40: 182.827 | J40: 165.79097 | K40: 166.05856 | L40: 165.79097 | M40: 18.083504 | N40: 16.497934 | O40: 16.317469 | P40: 16.359963 | Q40: 0 | S40: 2030 | T40: 81.477722 | U40: TRUE | V40: 0.43 | W40: 30.554146 | Z40: 14.468 | AA40: 21.296 | AB40: 25.8 | AC40: 0 | AD40: 0
A41: 2_b | B41: =VLOOKUP(A41,PIPE!A:D,4,0) -> 448.83 | C41: 1 | D41: 26 | E41: 328.74 | F41: 448.83 | G41: (11, 4) | H41: ('E', 'K') | I41: 150 | J41: 72.707486 | K41: 165.01135 | L41: 72.707486 | M41: 25 | N41: 11.520584 | O41: 22.149578 | P41: 11.01168 | Q41: 1 | R41: 2045 | S41: 2045 | T41: 313.88301 | U41: FALSE | V41: 2 | W41: 0 | X41: 50 | Y41: 10 | Z41: 0 | AA41: 0 | AB41: 0 | AC41: 45.329021 | AD41: 55.110648
A42: 60_b | B42: =VLOOKUP(A42,PIPE!A:D,4,0) -> 127.1 | C42: 1 | D42: 30 | E42: 42.53 | F42: 127.1 | G42: (21, 6) | H42: ('S', 'K') | I42: 136.22208 | J42: 100.32865 | K42: 179.01288 | L42: 100.32865 | M42: 23.788198 | N42: 19.956305 | O42: 19.662083 | P42: 19.633161 | Q42: 0 | S42: 2050 | T42: 83.447489 | U42: FALSE | V42: 2 | W42: 0 | Z42: 0 | AA42: 0 | AB42: 0 | AC42: 0 | AD42: 18.68
A43: 59_b | B43: =VLOOKUP(A43,PIPE!A:D,4,0) -> 356.04 | C43: 0 | E43: 154.52 | F43: 356.04 | G43: (20, 18) | H43: ('S', 'E') | U43: FALSE
A44: 50_a | B44: =VLOOKUP(A44,PIPE!A:D,4,0) -> 561.51 | C44: 0 | E44: 229 | F44: 561.51 | G44: (13, 15) | H44: ('E', 'E') | U44: FALSE
A45: 70_b | B45: =VLOOKUP(A45,PIPE!A:D,4,0) -> 369.46 | C45: 0 | E45: 305.38 | F45: 369.46 | G45: (19, 16) | H45: ('S', 'E') | U45: FALSE
A46: 30_b | B46: =VLOOKUP(A46,PIPE!A:D,4,0) -> 243.08 | C46: 0 | E46: 199.06 | F46: 243.08 | G46: (19, 13) | H46: ('S', 'E') | U46: FALSE
A47: 0_a | B47: =VLOOKUP(A47,PIPE!A:D,4,0) -> 423.46 | C47: 0 | E47: 302.33 | F47: 423.46 | G47: (4, 5) | H47: ('K', 'K') | U47: FALSE
A48: 34_a | B48: =VLOOKUP(A48,PIPE!A:D,4,0) -> 553.72 | C48: 0 | E48: 353.64 | F48: 553.72 | G48: (11, 12) | H48: ('E', 'E') | U48: FALSE
A49: 7_b | B49: =VLOOKUP(A49,PIPE!A:D,4,0) -> 518.06 | C49: 0 | E49: 167.02 | F49: 518.06 | G49: (17, 6) | H49: ('E', 'K') | U49: FALSE
A50: 29_a | B50: =VLOOKUP(A50,PIPE!A:D,4,0) -> 78.12 | C50: 0 | E50: 78.12 | F50: 78.12 | G50: (5, 12) | H50: ('K', 'E') | U50: FALSE
A51: 10_b | B51: =VLOOKUP(A51,PIPE!A:D,4,0) -> 141.73 | C51: 0 | E51: 132.71 | F51: 141.73 | G51: (22, 18) | H51: ('S', 'E') | U51: FALSE
A52: 2_a | B52: =VLOOKUP(A52,PIPE!A:D,4,0) -> 448.83 | C52: 0 | E52: 120.09 | F52: 448.83 | G52: (4, 11) | H52: ('K', 'E') | U52: FALSE
A53: 68_a | B53: =VLOOKUP(A53,PIPE!A:D,4,0) -> 189.69 | C53: 0 | E53: 29.03 | F53: 189.69 | G53: (12, 19) | H53: ('E', 'S') | U53: FALSE
A54: 1_a | B54: =VLOOKUP(A54,PIPE!A:D,4,0) -> 491.3 | C54: 0 | E54: 350.21 | F54: 491.3 | G54: (19, 27) | H54: ('S', 'A') | U54: FALSE
... A81: 9_b | B81: =VLOOKUP(A81,PIPE!A:D,4,0) -> 484.78 | C81: 0 | E81: 2.5 | F81: 484.78 | G81: (23, 15) | H81: ('S', 'E') | U81: FALSE
A82: 41_a | B82: =VLOOKUP(A82,PIPE!A:D,4,0) -> 100.6 | C82: 1 | D82: 6 | E82: 0 | F82: 100.6 | G82: (12, 20) | H82: ('E', 'S') | I82: 150 | J82: 135.08749 | K82: 186.57914 | L82: 135.08749 | M82: 25 | N82: 7.6853824 | O82: 17.454017 | P82: 7.4880925 | Q82: 1 | R82: 2050 | S82: 2050 | T82: 13.351023 | U82: FALSE | V82: 2 | W82: 0 | X82: 50 | Y82: 10 | Z82: 0 | AA82: 0 | AB82: 0 | AC82: 0 | AD82: 1.7860207
A83: 10_a | B83: =VLOOKUP(A83,PIPE!A:D,4,0) -> 141.73 | C83: 1 | D83: 22 | E83: 9.01 | F83: 141.73 | G83: (18, 22) | H83: ('E', 'S') | I83: 150 | J83: 127.59719 | K83: 178.00921 | L83: 127.59719 | M83: 25 | N83: 23.135811 | O83: 25.086203 | P83: 15.119394 | Q83: 1 | R83: 2045 | S83: 2045 | T83: 83.786518 | U83: FALSE | V83: 2 | W83: 0 | X83: 50 | Y83: 10 | Z83: 0 | AA83: 0 | AB83: 0 | AC83: 0 | AD83: 29.59
A84: 47_b | B84: =VLOOKUP(A84,PIPE!A:D,4,0) -> 562.63 | C84: 0 | E84: 530.62 | F84: 562.63 | G84: (26, 12) | H84: ('A', 'E') | U84: FALSE
A85: 0_b | B85: =VLOOKUP(A85,PIPE!A:D,4,0) -> 423.46 | C85: 0 | E85: 121.13 | F85: 423.46 | G85: (5, 4) | H85: ('K', 'K') | U85: FALSE
A86: 54_b | B86: =VLOOKUP(A86,PIPE!A:D,4,0) -> 45.28 | C86: 1 | D86: 26 | E86: 8.05 | F86: 45.28 | G86: (20, 5) | H86: ('S', 'K') | I86: 195.23118 | J86: 193.1305 | K86: 202.59039 | L86: 193.1305 | M86: 22.227783 | N86: 21.478355 | O86: 19.230671 | P86: 19.277065 | Q86: 0 | S86: 2050 | T86: 24.166303 | U86: FALSE | V86: 2 | W86: 0 | Z86: 0 | AA86: 0 | AB86: 0 | AC86: 0 | AD86: 48.586021
A87: 47_a | B87: =VLOOKUP(A87,PIPE!A:D,4,0) -> 562.63 | C87: 0 | E87: 31.51 | F87: 562.63 | G87: (12, 26) | H87: ('E', 'A') | U87: FALSE
A88: 13_a | B88: =VLOOKUP(A88,PIPE!A:D,4,0) -> 343.97 | C88: 0 | E88: 160.72 | F88: 343.97 | G88: (20, 22) | H88: ('S', 'S') | U88: FALSE
A89: 28_a | B89: =VLOOKUP(A89,PIPE!A:D,4,0) -> 496.16 | C89: 0 | E89: 207.57 | F89: 496.16 | G89: (13, 16) | H89: ('E', 'E') | U89: FALSE
A90: 62_a | B90: =VLOOKUP(A90,PIPE!A:D,4,0) -> 147.41 | C90: 0 | E90: 85.74 | F90: 147.41 | G90: (10, 22) | H90: ('E', 'S') | U90: FALSE
A91: 17_b | B91: =VLOOKUP(A91,PIPE!A:D,4,0) -> 336.49 | C91: 0 | E91: 40.56 | F91: 336.49 | G91: (25, 11) | H91: ('A', 'E') | U91: FALSE
A92: 5_a | B92: =VLOOKUP(A92,PIPE!A:D,4,0) -> 80.23 | C92: 1 | D92: 30 | E92: 65.69 | F92: 80.23 | G92: (13, 23) | H92: ('E', 'S') | I92: 150 | J92: 108.84972 | K92: 142.61203 | L92: 108.84972 | M92: 25 | N92: 19.979067 | O92: 20.615835 | P92: 19.584348 | Q92: 0 | S92: 2030 | T92: 151.97322 | U92: FALSE | V92: 2 | W92: 0 | Z92: 54.72 | AA92: 57.46 | AB92: 60.52 | AC92: 63.92 | AD92: 67.67
A93: 32_b | B93: =VLOOKUP(A93,PIPE!A:D,4,0) -> 345.18 | C93: 0 | E93: 41.52 | F93: 345.18 | G93: (21, 5) | H93: ('S', 'K') | U93: FALSE
A94: 49_b | B94: =VLOOKUP(A94,PIPE!A:D,4,0) -> 302.06 | C94: 0 | E94: 48.51 | F94: 302.06 | G94: (25, 17) | H94: ('A', 'E') | U94: FALSE
A95: 25_b | B95: =VLOOKUP(A95,PIPE!A:D,4,0) -> 297.08 | C95: 0 | E95: 109.53 | F95: 297.08 | G95: (27, 16) | H95: ('A', 'E') | U95: FALSE
A96: 9_a | B96: =VLOOKUP(A96,PIPE!A:D,4,0) -> 484.78 | C96: 0 | E96: 482.28 | F96: 484.78 | G96: (15, 23) | H96: ('E', 'S') | U96: FALSE
A97: 53_a | B97: =VLOOKUP(A97,PIPE!A:D,4,0) -> 371.42 | C97: 0 | E97: 339.39 | F97: 371.42 | G97: (5, 14) | H97: ('K', 'E') | U97: FALSE
A98: 18_a | B98: =VLOOKUP(A98,PIPE!A:D,4,0) -> 135.33 | C98: 0 | E98: 0 | F98: 135.33 | G98: (9, 28) | H98: ('E', 'A')
A99: 71_a | B99: =VLOOKUP(A99,PIPE!A:D,4,0) -> 192.08 | C99: 0 | E99: 0 | F99: 192.08 | G99: (8, 9) | H99: ('E', 'E')
A100: 52_a | B100: =VLOOKUP(A100,PIPE!A:D,4,0) -> 25.73 | C100: 0 | E100: 0 | F100: 25.73 | G100: (2, 26) | H100: ('S', 'A')
A101: 71_b | B101: =VLOOKUP(A101,PIPE!A:D,4,0) -> 192.08 | C101: 0 | E101: 0 | F101: 192.08 | G101: (9, 8) | H101: ('E', 'E')
A102: 11_a | B102: =VLOOKUP(A102,PIPE!A:D,4,0) -> 24.61 | C102: 0 | E102: 0 | F102: 24.61 | G102: (1, 25) | H102: ('S', 'A')
A103: 20_b | B103: =VLOOKUP(A103,PIPE!A:D,4,0) -> 25.42 | C103: 1 | D103: 38 | E103: 0 | F103: 25.42 | G103: (27, 3) | H103: ('A', 'S') | I103: 238.75987 | K103: 236.95987 | L103: 236.95987 | M103: 27.357529 | O103: 15 | Q103: 0 | S103: 2045 | T103: 50.548483 | W103: 0 | Z103: 0 | AA103: 0 | AB103: 0 | AC103: 106.29502 | AD103: 110.85
A104: 46_b | B104: =VLOOKUP(A104,PIPE!A:D,4,0) -> 161.79 | C104: 0 | E104: 0 | F104: 161.79 | G104: (8, 7) | H104: ('E', 'E')
A105: 18_b | B105: =VLOOKUP(A105,PIPE!A:D,4,0) -> 135.33 | C105: 0 | E105: 0 | F105: 135.33 | G105: (28, 9) | H105: ('A', 'E')
A106: 20_a | B106: =VLOOKUP(A106,PIPE!A:D,4,0) -> 25.42 | C106: 0 | E106: 0 | F106: 25.42 | G106: (3, 27) | H106: ('S', 'A')
A107: 11_b | B107: =VLOOKUP(A107,PIPE!A:D,4,0) -> 24.61 | C107: 0 | E107: 0 | F107: 24.61 | G107: (25, 1) | H107: ('A', 'S')
A108: 52_b | B108: =VLOOKUP(A108,PIPE!A:D,4,0) -> 25.73 | C108: 1 | D108: 42 | E108: 0 | F108: 25.73 | G108: (26, 2) | H108: ('A', 'S') | I108: 153.46191 | K108: 151.84191 | L108: 151.84191 | M108: 22.189588 | O108: 15 | Q108: 0 | S108: 2035 | T108: 98.422962 | W108: 0 | Z108: 0 | AA108: 107.738 | AB108: 131.33 | AC108: 83.130979 | AD108: 71.959352
A109: 46_a | B109: =VLOOKUP(A109,PIPE!A:D,4,0) -> 161.79 | C109: 0 | E109: 0 | F109: 161.79 | G109: (7, 8) | H109: ('E', 'E')

Sheet EUS - Sinks capacity evolution
A1: Sink node | B1: Initial capacity [Mt] | C1: 2030 capacity [Mt] | D1: 2035 capacity [Mt] | E1: 2040 capacity [Mt] | F1: 2045 capacity [Mt] | G1: 2050 capacity [Mt] | H1: Final capacity [Mt]
A2: 1 | B2: 1250 | C2: 1250 | D2: 1250 | E2: 1250 | F2: 1250 | G2: 1250 | H2: 1250
A3: 2 | B3: 3790 | C3: 3790 | D3: 3790 | E3: 3682.262 | F3: 3550.932 | G3: 3467.801 | H3: 3395.8417
A4: 3 | B4: 2100 | C4: 2100 | D4: 2100 | E4: 2100 | F4: 2100 | G4: 1993.705 | H4: 1882.855
A5: 19 | B5: 6655.37 | C5: 6655.37 | D5: 6655.37 | E5: 6655.37 | F5: 6655.37 | G5: 6655.37 | H5: 6655.37
A6: 20 | B6: 4571.37 | C6: 4571.37 | D6: 4556.902 | E6: 4535.606 | F6: 4509.806 | G6: 4509.806 | H6: 4509.806
A7: 21 | B7: 1372.72 | C7: 1372.72 | D7: 1372.72 | E7: 1372.72 | F7: 1372.72 | G7: 1372.72 | H7: 1336.2894
A8: 22 | B8: 2171.48 | C8: 2171.48 | D8: 2171.48 | E8: 2171.48 | F8: 2117.964 | G8: 2048.204 | H8: 1992.702
A9: 23 | B9: 4632.05 | C9: 4632.05 | D9: 4577.33 | E9: 4519.87 | F9: 4459.35 | G9: 4395.43 | H9: 4327.76
A10: 24 | B10: 1319.75 | C10: 1319.75 | D10: 1319.75 | E10: 1319.75 | F10: 1319.75 | G10: 1319.75 | H10: 1319.75

Sheet EUS - Utilization evolution
A1: Utilization node | B1: Utilization capacity [Mt] | C1: 2030 utilization [Mt] | D1: 2035 utilization [Mt] | E1: 2040 utilization [Mt] | F1: 2045 utilization [Mt] | G1: 2050 utilization [Mt]
A2: 4 | B2: 150 | C2: 0 | D2: 0 | E2: 71.61 | F2: 119.53902 | G2: 132.39065
A3: 5 | B3: 75 | C3: 0 | D3: 3.534 | E3: 0 | F3: 26.413979 | G3: 75
A4: 6 | B4: 75 | C4: 0 | D4: 50.73 | E4: 49.362 | F4: 54.12 | G4: 75

Sheet EUS - Cost breakdown
A1: Concept | B1: 2030 | C1: 2035 | D1: 2040 | E1: 2045 | F1: 2050 | G1: Total
A2: Capture cost | B2: 5288.0388 | C2: 13947.111 | D2: 17218.78 | E2: 17416.629 | F2: 15763.771 | G2: 69634.329
A3: Injection cost | B3: 453.1814 | C3: 925.01024 | D3: 1022.2958 | E3: 920.8521 | F3: 739.60992 | G3: 4060.9495
A4: CAPEX onshore pipe | B4: 333.14629 | C4: 486.06006 | D4: 542.85929 | E4: 708.11027 | F4: 364.9733 | G4: 2435.1492
A5: CAPEX onshore pipe (insulation only) | B5: 30.554146 | C5: 0 | D5: 0 | E5: 0 | F5: 0 | G5: 30.554146
A6: CAPEX offshore pipe | B6: 0 | C6: 98.422962 | D6: 0 | E6: 50.548483 | F6: 0 | G6: 148.97145
A7: CAPEX initial boosting stations | B7: 5561.7063 | C7: 8725.7608 | D7: 5010.4662 | E7: 2800.7361 | F7: 1727.8934 | G7: 23826.563
A8: CAPEX additional boosting stations | B8: 0 | C8: 0 | D8: 269.94239 | E8: 337.96589 | F8: 117.29307 | G8: 725.20135
A9: OPEX onshore pipe | B9: 43.309138 | C9: 96.016401 | D9: 143.35202 | E9: 200.71455 | F9: 199.5891 | G9: 682.98121
A10: OPEX onshore pipe (insulation only) | B10: 3.9720485 | C10: 3.010823 | D10: 2.282275 | E10: 1.7298952 | F10: 1.3113016 | G10: 12.306343
A11: OPEX offshore pipe | B11: 0 | C11: 12.795014 | D11: 9.6986662 | E11: 13.9229 | F11: 10.553524 | G11: 46.970104
A12: OPEX initial boosting stations | B12: 150.22829 | C12: 349.6284 | D12: 400.158 | E12: 378.83054 | F12: 333.82173 | G12: 1612.667
A13: OPEX additional boosting stations | B13: 0 | C13: 0 | D13: 6.9380719 | E13: 13.971691 | F13: 13.576459 | G13: 34.486222
... A19: TOTAL | B19: 58155.742 | C19: 47741.387 | D19: 33269.554 | E19: 23682.041 | F19: 13019.452 | G19: 175868.18

Sheet PIPE
A1: Pipeline identifier | B1: Node connection | C1: Connection type | D1: Longitude (km)
A2: 0_a | B2: (4, 5) | C2: ('K', 'K') | D2: 423.46
A3: 0_b | B3: (5, 4) | C3: ('K', 'K') | D3: 423.46
A4: 1_a | B4: (19, 27) | C4: ('S', 'A') | D4: 491.3
A5: 1_b | B5: (27, 19) | C5: ('A', 'S') | D5: 491.3
A6: 2_a | B6: (4, 11) | C6: ('K', 'E') | D6: 448.83
A7: 2_b | B7: (11, 4) | C7: ('E', 'K') | D7: 448.83
A8: 3_a | B8: (4, 17) | C8: ('K', 'E') | D8: 68.85
A9: 3_b | B9: (17, 4) | C9: ('E', 'K') | D9: 68.85
A10: 4_a | B10: (6, 14) | C10: ('K', 'E') | D10: 151.35
A11: 4_b | B11: (14, 6) | C11: ('E', 'K') | D11: 151.35
A12: 5_a | B12: (13, 23) | C12: ('E', 'S') | D12: 80.23
A13: 5_b | B13: (23, 13) | C13: ('S', 'E') | D13: 80.23
... A109: 71_b | B109: (9, 8) | C109: ('E', 'E') | D109: 192.08

Sheet HUS - Pipes
A1: Pipe ID | B1: Installed | C1: Diameter [inch] | D1: Distance until highest point [km] | E1: Longitude [km] | F1: Node connections | G1: Node types | H1: Initial pressure [bar] | I1: Pressure at highest point [bar] | J1: Final pressure [bar] | K1: Lowest pressure [bar] | L1: Initial temperature [°C] | M1: Temperature at critical pressure point [°C] | N1: Final temperature [°C] | O1: Lowest temperature [°C] | P1: Number of boosters | Q1: Booster installation year | R1: Installation Year | S1: Present Value Cost [M€] | T1: Insulated | U1: U-value [W/m^2/K] | V1: Insulation cost [M€] | W1: Booster delta pressure [bar] | X1: Booster delta temperature [°C] | Y1: Flow in 2030 | Z1: Flow in 2035 | AA1: Flow in 2040 | AB1: Flow in 2045 | AC1: Flow in 2050
A2: 17_a | B2: 0 | D2: 295.43 | E2: 336.49 | F2: (11, 25) | G2: ('E', 'A') | T2: FALSE
A3: 4_a | B3: 0 | D3: 99.73 | E3: 151.35 | F3: (6, 14) | G3: ('K', 'E') | T3: FALSE
A4: 49_a | B4: 0 | D4: 165.53 | E4: 302.06 | F4: (17, 25) | G4: ('E', 'A') | T4: FALSE
A5: 36_a | B5: 0 | D5: 77.08 | E5: 325.83 | F5: (10, 20) | G5: ('E', 'S') | T5: FALSE
A6: 63_a | B6: 0 | D6: 313.27 | E6: 447.89 | F6: (11, 17) | G6: ('E', 'E') | T6: FALSE
A7: 40_b | B7: 0 | D7: 209.77 | E7: 326.42 | F7: (21, 20) | G7: ('S', 'S') | T7: FALSE
A8: 59_a | B8: 0 | D8: 201.52 | E8: 356.04 | F8: (18, 20) | G8: ('E', 'S') | T8: FALSE
A9: 25_a | B9: 1 | C9: 38 | D9: 186.05 | E9: 297.08 | F9: (16, 27) | G9: ('E', 'A') | H9: 150 | I9: 83.176683 | J9: 238.75987 | K9: 83.176683 | L9: 25 | M9: 15.521725 | N9: 27.357529 | O9: 15.4939 | P9: 1 | Q9: 2045 | R9: 2045 | S9: 310.44075 | T9: FALSE | U9: 2 | V9: 0 | W9: 50 | X9: 10 | Y9: 0 | Z9: 0 | AA9: 0 | AB9: 96.357372 | AC9: 110.85
A10: 37_b | B10: 0 | D10: 86.53 | E10: 347.61 | F10: (24, 5) | G10: ('S', 'K') | T10: FALSE
A11: 56_a | B11: 0 | D11: 41.05 | E11: 263.83 | F11: (15, 18) | G11: ('E', 'E') | T11: FALSE
A12: 31_a | B12: 1 | C12: 30 | D12: 85.68 | E12: 228.48 | F12: (15, 22) | G12: ('E', 'S') | H12: 150 | I12: 87.35104 | J12: 157.66753 | K12: 87.35104 | L12: 25 | M12: 18.302202 | N12: 25.322261 | O12: 15.341525 | P12: 1 | Q12: 2040 | R12: 2040 | S12: 250.32444 | T12: FALSE | U12: 2 | V12: 0 | W12: 50 | X12: 10 | Y12: 0 | Z12: 0 | AA12: 0 | AB12: 0 | AC12: 73.04
A13: 58_a | B13: 0 | D13: 164.64 | E13: 189.66 | F13: (4, 24) | G13: ('K', 'S') | T13: FALSE
A14: 31_b | B14: 0 | D14: 142.8 | E14: 228.48 | F14: (22, 15) | G14: ('S', 'E') | T14: FALSE
A15: 23_a | B15: 0 | D15: 38.1 | E15: 179.47 | F15: (14, 21) | G15: ('E', 'S') | T15: FALSE
A16: 44_b | B16: 0 | D16: 258.27 | E16: 348.87 | F16: (23, 12) | G16: ('S', 'E') | T16: FALSE
A17: 43_a | B17: 0 | D17: 148.58 | E17: 370.19 | F17: (14, 17) | G17: ('E', 'E') | T17: FALSE
A18: 29_b | B18: 1 | C18: 18 | D18: 0 | E18: 78.12 | F18: (12, 5) | G18: ('E', 'K') | H18: 150 | I18: 150 | J18: 182.827 | K18: 150 | L18: 25 | M18: 25 | N18: 18.083504 | O18: 18.10041 | P18: 0 | R18: 2030 | S18: 99.69535 | T18: FALSE | U18: 2 | V18: 0 | Y18: 14.468 | Z18: 24.83 | AA18: 25.8 | AB18: 26.413979 | AC18: 26.413979
A19: 13_b | B19: 1 | C19: 34 | D19: 183.25 | E19: 343.97 | F19: (22, 20) | G19: ('S', 'S') | H19: 178.00921 | I19: 72.949938 | J19: 195.23118 | K19: 72.949938 | L19: 25.086203 | M19: 12.702641 | N19: 22.227783 | O19: 12.206166 | P19: 1 | Q19: 2050 | R19: 2050 | S19: 244.00848 | T19: FALSE | U19: 2 | V19: 0 | W19: 50 | X19: 10 | Y19: 0 | Z19: 0 | AA19: 0 | AB19: 0 | AC19: 78.8045
A20: 43_b | B20: 0 | D20: 221.62 | E20: 370.19 | F20: (17, 14) | G20: ('E', 'E') | T20: FALSE
A21: 67_b | B21: 0 | D21: 85.34 | E21: 110.44 | F21: (26, 11) | G21: ('A', 'E') | T21: FALSE
A22: 51_a | B22: 0 | D22: 290.25 | E22: 463.4 | F22: (4, 12) | G22: ('K', 'E') | T22: FALSE
A23: 51_b | B23: 0 | D23: 173.15 | E23: 463.4 | F23: (12, 4) | G23: ('E', 'K') | T23: FALSE
A24: 3_b | B24: 1 | C24: 34 | D24: 57.79 | E24: 68.85 | F24: (17, 4) | G24: ('E', 'K') | H24: 150 | I24: 137.47836 | J24: 143.33677 | K24: 137.47836 | L24: 25 | M24: 21.998053 | N24: 21.839455 | O24: 21.759017 | P24: 0 | R24: 2035 | S24: 107.77334 | T24: FALSE | U24: 2 | V24: 0 | Y24: 0 | Z24: 69.47 | AA24: 71.61 | AB24: 74.21 | AC24: 77.28
A25: 14_a | B25: 1 | C25: 26 | D25: 147.03 | E25: 222.05 | F25: (10, 21) | G25: ('E', 'S') | H25: 150 | I25: 68.230718 | J25: 136.22208 | K25: 68.230718 | L25: 25 | M25: 14.398163 | N25: 23.788198 | O25: 13.25316 | P25: 1 | Q25: 2040 | R25: 2040 | S25: 210.84234 | T25: FALSE | U25: 2 | V25: 0 | W25: 50 | X25: 10 | Y25: 0 | Z25: 0 | AA25: 52.99 | AB25: 55.110648 | AC25: 55.110648
A26: 37_a | B26: 0 | D26: 261.08 | E26: 347.61 | F26: (5, 24) | G26: ('K', 'S') | T26: FALSE
A27: 3_a | B27: 0 | D27: 11.06 | E27: 68.85 | F27: (4, 17) | G27: ('K', 'E') | T27: FALSE
A28: 58_b | B28: 1 | C28: 6 | D28: 25.02 | E28: 189.66 | F28: (24, 4) | G28: ('S', 'K') | H28: 187.70383 | I28: 149.00597 | J28: 150.87785 | K28: 149.00597 | L28: 35.737413 | M28: 19.727869 | N28: 19.81856 | O28: 19.726547 | P28: 0 | R28: 2045 | S28: 31.557135 | T28: FALSE | U28: 2 | V28: 0 | Y28: 0 | Z28: 0 | AA28: 0 | AB28: 0 | AC28: 0
A29: 28_b | B29: 0 | D29: 288.59 | E29: 496.16 | F29: (16, 13) | G29: ('E', 'E') | T29: FALSE
A30: 67_a | B30: 1 | C30: 42 | D30: 12.05 | E30: 110.44 | F30: (11, 26) | G30: ('E', 'A') | H30: 150 | I30: 104.45679 | J30: 153.46191 | K30: 104.45679 | L30: 25 | M30: 22.20149 | N30: 22.189588 | O30: 22.206751 | P30: 0 | R30: 2035 | S30: 216.29825 | T30: FALSE | U30: 2 | V30: 0 | Y30: 0 | Z30: 90.062 | AA30: 131.33 | AB30: 38.205128 | AC30: 0
A31: 44_a | B31: 0 | D31: 90.6 | E31: 348.87 | F31: (12, 23) | G31: ('E', 'S') | T31: FALSE
A32: 34_b | B32: 0 | D32: 200.08 | E32: 553.72 | F32: (12, 11) | G32: ('E', 'E') | T32: FALSE
A33: 32_a | B33: 0 | D33: 303.66 | E33: 345.18 | F33: (5, 21) | G33: ('K', 'S') | T33: FALSE
A34: 64_a | B34: 0 | D34: 222.05 | E34: 245.06 | F34: (17, 24) | G34: ('E', 'S') | T34: FALSE
A35: 61_a | B35: 0 | D35: 229.52 | E35: 233.52 | F35: (18, 23) | G35: ('E', 'S') | T35: FALSE
A36: 62_b | B36: 0 | D36: 61.67 | E36: 147.41 | F36: (22, 10) | G36: ('S', 'E') | T36: FALSE
A37: 4_b | B37: 1 | C37: 38 | D37: 51.62 | E37: 151.35 | F37: (14, 6) | G37: ('E', 'K') | H37: 150 | I37: 100.14645 | J37: 205.93858 | K37: 100.14645 | L37: 25 | M37: 20.372963 | N37: 21.169234 | O37: 20.653032 | P37: 0 | R37: 2040 | S37: 204.48032 | T37: FALSE | U37: 2 | V37: 0 | Y37: 0 | Z37: 0 | AA37: 52.26 | AB37: 54.12 | AC37: 56.32
A38: 16_a | B38: 0 | D38: 30.51 | E38: 555.74 | F38: (12, 27) | G38: ('E', 'A') | T38: FALSE
A39: 5_b | B39: 0 | D39: 14.54 | E39: 80.23 | F39: (23, 13) | G39: ('S', 'E') | T39: FALSE
A40: 54_a | B40: 1 | C40: 18 | D40: 37.23 | E40: 45.28 | F40: (5, 20) | G40: ('K', 'S') | H40: 182.827 | I40: 165.79097 | J40: 166.05856 | K40: 165.79097 | L40: 18.083504 | M40: 16.497934 | N40: 16.317469 | O40: 16.359963 | P40: 0 | R40: 2030 | S40: 81.477722 | T40: TRUE | U40: 0.43 | V40: 30.554146 | Y40: 14.468 | Z40: 12.904 | AA40: 21.202 | AB40: 0 | AC40: 0
A41: 2_b | B41: 1 | C41: 42 | D41: 328.74 | E41: 448.83 | F41: (11, 4) | G41: ('E', 'K') | H41: 150 | I41: 84.170439 | J41: 180.87785 | K41: 84.170439 | L41: 25 | M41: 14.313618 | N41: 24.81856 | O41: 13.871772 | P41: 1 | Q41: 2045 | R41: 2045 | S41: 507.04142 | T41: FALSE | U41: 2 | V41: 0 | W41: 50 | X41: 10 | Y41: 0 | Z41: 0 | AA41: 0 | AB41: 90.254872 | AC41: 127.07
A42: 60_b | B42: 1 | C42: 30 | D42: 42.53 | E42: 127.1 | F42: (21, 6) | G42: ('S', 'K') | H42: 136.22208 | I42: 100.32865 | J42: 179.01288 | K42: 100.32865 | L42: 23.788198 | M42: 19.956305 | N42: 19.662083 | O42: 19.633161 | P42: 0 | R42: 2040 | S42: 145.23508 | T42: FALSE | U42: 2 | V42: 0 | Y42: 0 | Z42: 0 | AA42: 52.99 | AB42: 55.110648 | AC42: 55.110648
A43: 59_b | B43: 0 | D43: 154.52 | E43: 356.04 | F43: (20, 18) | G43: ('S', 'E') | T43: FALSE
A44: 50_a | B44: 0 | D44: 229 | E44: 561.51 | F44: (13, 15) | G44: ('E', 'E') | T44: FALSE
A45: 70_b | B45: 0 | D45: 305.38 | E45: 369.46 | F45: (19, 16) | G45: ('S', 'E') | T45: FALSE
A46: 30_b | B46: 0 | D46: 199.06 | E46: 243.08 | F46: (19, 13) | G46: ('S', 'E') | T46: FALSE
A47: 0_a | B47: 0 | D47: 302.33 | E47: 423.46 | F47: (4, 5) | G47: ('K', 'K') | T47: FALSE
A48: 34_a | B48: 0 | D48: 353.64 | E48: 553.72 | F48: (11, 12) | G48: ('E', 'E') | T48: FALSE
A49: 7_b | B49: 0 | D49: 167.02 | E49: 518.06 | F49: (17, 6) | G49: ('E', 'K') | T49: FALSE
A50: 29_a | B50: 0 | D50: 78.12 | E50: 78.12 | F50: (5, 12) | G50: ('K', 'E') | T50: FALSE
A51: 10_b | B51: 0 | D51: 132.71 | E51: 141.73 | F51: (22, 18) | G51: ('S', 'E') | T51: FALSE
A52: 2_a | B52: 0 | D52: 120.09 | E52: 448.83 | F52: (4, 11) | G52: ('K', 'E') | T52: FALSE
A53: 68_a | B53: 0 | D53: 29.03 | E53: 189.69 | F53: (12, 19) | G53: ('E', 'S') | T53: FALSE
A54: 1_a | B54: 0 | D54: 350.21 | E54: 491.3 | F54: (19, 27) | G54: ('S', 'A') | T54: FALSE
... A81: 9_b | B81: 0 | D81: 2.5 | E81: 484.78 | F81: (23, 15) | G81: ('S', 'E') | T81: FALSE
A82: 41_a | B82: 1 | C82: 6 | D82: 0 | E82: 100.6 | F82: (12, 20) | G82: ('E', 'S') | H82: 150 | I82: 135.08749 | J82: 186.57914 | K82: 135.08749 | L82: 25 | M82: 7.6853824 | N82: 17.454017 | O82: 7.4880925 | P82: 1 | Q82: 2050 | R82: 2050 | S82: 13.351023 | T82: FALSE | U82: 2 | V82: 0 | W82: 50 | X82: 10 | Y82: 0 | Z82: 0 | AA82: 0 | AB82: 0 | AC82: 1.7860207
A83: 10_a | B83: 1 | C83: 22 | D83: 9.01 | E83: 141.73 | F83: (18, 22) | G83: ('E', 'S') | H83: 150 | I83: 127.59719 | J83: 178.00921 | K83: 127.59719 | L83: 25 | M83: 23.135811 | N83: 25.086203 | O83: 15.119394 | P83: 1 | Q83: 2045 | R83: 2045 | S83: 83.786518 | T83: FALSE | U83: 2 | V83: 0 | W83: 50 | X83: 10 | Y83: 0 | Z83: 0 | AA83: 0 | AB83: 28.51 | AC83: 29.59
A84: 47_b | B84: 0 | D84: 530.62 | E84: 562.63 | F84: (26, 12) | G84: ('A', 'E') | T84: FALSE
A85: 0_b | B85: 0 | D85: 121.13 | E85: 423.46 | F85: (5, 4) | G85: ('K', 'K') | T85: FALSE
A86: 54_b | B86: 1 | C86: 34 | D86: 8.05 | E86: 45.28 | F86: (20, 5) | G86: ('S', 'K') | H86: 195.23118 | I86: 193.31485 | J86: 203.54655 | K86: 193.31485 | L86: 22.227783 | M86: 21.639465 | N86: 20.017965 | O86: 20.054899 | P86: 0 | R86: 2050 | S86: 31.602059 | T86: FALSE | U86: 2 | V86: 0 | Y86: 0 | Z86: 0 | AA86: 0 | AB86: 0 | AC86: 80.590521
A87: 47_a | B87: 0 | D87: 31.51 | E87: 562.63 | F87: (12, 26) | G87: ('E', 'A') | T87: FALSE
A88: 13_a | B88: 0 | D88: 160.72 | E88: 343.97 | F88: (20, 22) | G88: ('S', 'S') | T88: FALSE
A89: 28_a | B89: 0 | D89: 207.57 | E89: 496.16 | F89: (13, 16) | G89: ('E', 'E') | T89: FALSE
A90: 62_a | B90: 0 | D90: 85.74 | E90: 147.41 | F90: (10, 22) | G90: ('E', 'S') | T90: FALSE
A91: 17_b | B91: 0 | D91: 40.56 | E91: 336.49 | F91: (25, 11) | G91: ('A', 'E') | T91: FALSE
A92: 5_a | B92: 1 | C92: 30 | D92: 65.69 | E92: 80.23 | F92: (13, 23) | G92: ('E', 'S') | H92: 150 | I92: 108.84972 | J92: 142.61203 | K92: 108.84972 | L92: 25 | M92: 19.979067 | N92: 20.615835 | O92: 19.584348 | P92: 0 | R92: 2030 | S92: 151.97322 | T92: FALSE | U92: 2 | V92: 0 | Y92: 54.72 | Z92: 57.46 | AA92: 60.52 | AB92: 63.92 | AC92: 67.67
A93: 32_b | B93: 0 | D93: 41.52 | E93: 345.18 | F93: (21, 5) | G93: ('S', 'K') | T93: FALSE
A94: 49_b | B94: 0 | D94: 48.51 | E94: 302.06 | F94: (25, 17) | G94: ('A', 'E') | T94: FALSE
A95: 25_b | B95: 0 | D95: 109.53 | E95: 297.08 | F95: (27, 16) | G95: ('A', 'E') | T95: FALSE
A96: 9_a | B96: 0 | D96: 482.28 | E96: 484.78 | F96: (15, 23) | G96: ('E', 'S') | T96: FALSE
A97: 53_a | B97: 0 | D97: 339.39 | E97: 371.42 | F97: (5, 14) | G97: ('K', 'E') | T97: FALSE
A98: 18_a | B98: 0 | D98: 0 | E98: 135.33 | F98: (9, 28) | G98: ('E', 'A')
A99: 71_a | B99: 0 | D99: 0 | E99: 192.08 | F99: (8, 9) | G99: ('E', 'E')
A100: 52_a | B100: 0 | D100: 0 | E100: 25.73 | F100: (2, 26) | G100: ('S', 'A')
A101: 71_b | B101: 0 | D101: 0 | E101: 192.08 | F101: (9, 8) | G101: ('E', 'E')
A102: 11_a | B102: 0 | D102: 0 | E102: 24.61 | F102: (1, 25) | G102: ('S', 'A')
A103: 20_b | B103: 1 | C103: 38 | D103: 0 | E103: 25.42 | F103: (27, 3) | G103: ('A', 'S') | H103: 238.75987 | J103: 236.95987 | K103: 236.95987 | L103: 27.357529 | N103: 15 | P103: 0 | R103: 2045 | S103: 50.548483 | V103: 0 | Y103: 0 | Z103: 0 | AA103: 0 | AB103: 96.357372 | AC103: 110.85
A104: 46_b | B104: 0 | D104: 0 | E104: 161.79 | F104: (8, 7) | G104: ('E', 'E')
A105: 18_b | B105: 0 | D105: 0 | E105: 135.33 | F105: (28, 9) | G105: ('A', 'E')
A106: 20_a | B106: 0 | D106: 0 | E106: 25.42 | F106: (3, 27) | G106: ('S', 'A')
A107: 11_b | B107: 0 | D107: 0 | E107: 24.61 | F107: (25, 1) | G107: ('A', 'S')
A108: 52_b | B108: 1 | C108: 42 | D108: 0 | E108: 25.73 | F108: (26, 2) | G108: ('A', 'S') | H108: 153.46191 | J108: 151.84191 | K108: 151.84191 | L108: 22.189588 | N108: 15 | P108: 0 | R108: 2035 | S108: 98.422962 | V108: 0 | Y108: 0 | Z108: 90.062 | AA108: 131.33 | AB108: 38.205128 | AC108: 0
A109: 46_a | B109: 0 | D109: 0 | E109: 161.79 | F109: (7, 8) | G109: ('E', 'E')

Sheet HUS - Sinks capacity evolution
A1: Sink node | B1: Initial capacity [Mt] | C1: 2030 capacity [Mt] | D1: 2035 capacity [Mt] | E1: 2040 capacity [Mt] | F1: 2045 capacity [Mt] | G1: 2050 capacity [Mt] | H1: Final capacity [Mt]
A2: 1 | B2: 1250 | C2: 1250 | D2: 1250 | E2: 1250 | F2: 1250 | G2: 1250 | H2: 1250
A3: 2 | B3: 3790 | C3: 3790 | D3: 3790 | E3: 3699.938 | F3: 3568.608 | G3: 3530.4029 | H3: 3530.4029
A4: 3 | B4: 2100 | C4: 2100 | D4: 2100 | E4: 2100 | F4: 2100 | G4: 2003.6426 | H4: 1892.7926
A5: 19 | B5: 6655.37 | C5: 6655.37 | D5: 6655.37 | E5: 6655.37 | F5: 6655.37 | G5: 6655.37 | H5: 6655.37
A6: 20 | B6: 4571.37 | C6: 4571.37 | D6: 4556.902 | E6: 4543.998 | F6: 4522.796 | G6: 4522.796 | H6: 4522.796
A7: 21 | B7: 1372.72 | C7: 1372.72 | D7: 1372.72 | E7: 1372.72 | F7: 1372.72 | G7: 1372.72 | H7: 1372.72
A8: 22 | B8: 2171.48 | C8: 2171.48 | D8: 2171.48 | E8: 2171.48 | F8: 2171.48 | G8: 2142.97 | H8: 2119.1445
A9: 23 | B9: 4632.05 | C9: 4632.05 | D9: 4577.33 | E9: 4519.87 | F9: 4459.35 | G9: 4395.43 | H9: 4327.76
A10: 24 | B10: 1319.75 | C10: 1319.75 | D10: 1319.75 | E10: 1319.75 | F10: 1319.75 | G10: 1319.75 | H10: 1319.75

Sheet HUS - Utilization evolution
A1: Utilization node | B1: Utilization capacity [Mt] | C1: 2030 utilization [Mt] | D1: 2035 utilization [Mt] | E1: 2040 utilization [Mt] | F1: 2045 utilization [Mt] | G1: 2050 utilization [Mt]
A2: 4 | B2: 225 | C2: 0 | D2: 69.47 | E2: 71.61 | F2: 164.46487 | G2: 204.35
A3: 5 | B3: 112.5 | C3: 0 | D3: 11.926 | E3: 4.598 | F3: 26.413979 | G3: 107.0045
A4: 6 | B4: 112.5 | C4: 0 | D4: 0 | E4: 105.25 | F4: 109.23065 | G4: 111.43065

Sheet HUS - Cost breakdown
A1: Concept | B1: 2030 | C1: 2035 | D1: 2040 | E1: 2045 | F1: 2050 | G1: Total
A2: Capture cost | B2: 5288.0388 | C2: 14008.748 | D2: 17322.934 | E2: 17547.226 | F2: 15772.046 | G2: 69938.993
A3: Injection cost | B3: 453.1814 | C3: 795.71296 | D3: 803.20604 | E3: 646.92862 | F3: 437.06628 | G3: 3136.0953
A4: CAPEX onshore pipe | B4: 333.14629 | C4: 324.07159 | D4: 810.88219 | E4: 932.82582 | F4: 288.96156 | G4: 2689.8875
A5: CAPEX onshore pipe (insulation only) | B5: 30.554146 | C5: 0 | D5: 0 | E5: 0 | F5: 0 | G5: 30.554146
A6: CAPEX offshore pipe | B6: 0 | C6: 98.422962 | D6: 0 | E6: 50.548483 | F6: 0 | G6: 148.97145
A7: CAPEX initial boosting stations | B7: 5561.7063 | C7: 9647.4559 | D7: 3898.1774 | E7: 3548.357 | F7: 1398.8621 | G7: 24054.559
A8: CAPEX additional boosting stations | B8: 0 | C8: 0 | D8: 269.94239 | E8: 479.17437 | F8: 117.29307 | G8: 866.40983
A9: OPEX onshore pipe | B9: 43.309138 | C9: 74.957841 | D9: 162.23245 | E9: 244.2406 | F9: 222.70033 | G9: 747.44036
A10: OPEX onshore pipe (insulation only) | B10: 3.9720485 | C10: 3.010823 | D10: 2.282275 | E10: 1.7298952 | F10: 1.3113016 | G10: 12.306343
A11: OPEX offshore pipe | B11: 0 | C11: 12.795014 | D11: 9.6986662 | E11: 13.9229 | F11: 10.553524 | G11: 46.970104
A12: OPEX initial boosting stations | B12: 150.22829 | C12: 374.52888 | D12: 388.989 | E12: 390.5473 | F12: 333.82173 | G12: 1638.1152
A13: OPEX additional boosting stations | B13: 0 | C13: 0 | D13: 6.9380719 | E13: 17.608341 | F13: 16.326122 | G13: 40.872535
... A19: TOTAL | B19: 58155.742 | C19: 46221.381 | D19: 28552.211 | E19: 19891.854 | F19: 7505.6681 | G19: 160326.86

Sheet Network length per scenario
A1: Scenario | B1: 2030 | C1: 2035 | D1: 2040 | E1: 2045 | F1: 2050
A2: LUS | B2: 203.63 | C2: 408.65 | D2: 859.18 | E2: 1323.41 | F2: 2218.81
A3: EUS | B3: 203.63 | C3: 491.15 | D3: 1010.53 | E3: 1923.59 | F3: 2540.54
A4: HUS | B4: 203.63 | C4: 408.65 | D4: 1137.63 | E4: 2240.35 | F4: 2730.2
